{
  "month": 2,
  "bestDestinations": [
    {
      "regionId": "chiang-mai",
      "category": "mountain",
      "reason": "평균 24°C의 쾌적한 기온, 비가 거의 없는 맑은 날씨, 풍부한 일조량",
      "rating": 5
    },
    {
      "regionId": "hawaii",
      "category": "beach",
      "reason": "평균 23°C의 쾌적한 기온, 비가 거의 없는 맑은 날씨, 풍부한 일조량",
      "rating": 5
    },
    {
      "regionId": "ho-chi-minh",
      "category": "city",
      "reason": "평균 29°C의 온화한 날씨, 비가 거의 없는 맑은 날씨, 풍부한 일조량",
      "rating": 5
    },
    {
      "regionId": "manila",
      "category": "city",
      "reason": "평균 27°C의 쾌적한 기온, 비가 거의 없는 맑은 날씨, 풍부한 일조량",
      "rating": 5
    },
    {
      "regionId": "kaohsiung",
      "category": "city",
      "reason": "평균 21°C의 쾌적한 기온, 비가 거의 없는 맑은 날씨, 풍부한 일조량",
      "rating": 5
    },
    {
      "regionId": "seville",
      "category": "culture",
      "reason": "평균 14°C, 비가 거의 없는 맑은 날씨, 풍부한 일조량",
      "rating": 5
    },
    {
      "regionId": "rome",
      "category": "culture",
      "reason": "평균 10°C, 비가 거의 없는 맑은 날씨, 풍부한 일조량",
      "rating": 5
    },
    {
      "regionId": "athens",
      "category": "culture",
      "reason": "평균 10°C, 비가 거의 없는 맑은 날씨, 풍부한 일조량",
      "rating": 5
    },
    {
      "regionId": "bangkok",
      "category": "culture",
      "reason": "평균 28°C의 온화한 날씨, 비가 거의 없는 맑은 날씨, 풍부한 일조량",
      "rating": 4
    },
    {
      "regionId": "phuket",
      "category": "beach",
      "reason": "평균 28°C의 온화한 날씨, 비가 거의 없는 맑은 날씨, 풍부한 일조량",
      "rating": 4
    },
    {
      "regionId": "nice",
      "category": "beach",
      "reason": "평균 10°C, 강수량 적음, 풍부한 일조량",
      "rating": 4
    },
    {
      "regionId": "los-angeles",
      "category": "city",
      "reason": "평균 14°C, 강수량 적음, 풍부한 일조량",
      "rating": 4
    },
    {
      "regionId": "melbourne",
      "category": "culture",
      "reason": "평균 20°C의 온화한 날씨, 비가 거의 없는 맑은 날씨, 풍부한 일조량",
      "rating": 4
    },
    {
      "regionId": "hanoi",
      "category": "city",
      "reason": "평균 19°C의 온화한 날씨, 강수량 적음",
      "rating": 4
    },
    {
      "regionId": "da-nang",
      "category": "beach",
      "reason": "평균 23°C의 쾌적한 기온, 강수량 적음, 풍부한 일조량",
      "rating": 4
    },
    {
      "regionId": "boracay",
      "category": "beach",
      "reason": "평균 26°C의 쾌적한 기온, 풍부한 일조량",
      "rating": 4
    },
    {
      "regionId": "cebu",
      "category": "beach",
      "reason": "평균 27°C의 쾌적한 기온, 풍부한 일조량",
      "rating": 4
    },
    {
      "regionId": "singapore",
      "category": "city",
      "reason": "평균 27°C의 쾌적한 기온, 풍부한 일조량",
      "rating": 4
    },
    {
      "regionId": "lombok",
      "category": "beach",
      "reason": "평균 26°C의 쾌적한 기온, 풍부한 일조량",
      "rating": 4
    },
    {
      "regionId": "taipei",
      "category": "city",
      "reason": "평균 18°C의 온화한 날씨, 강수량 적음",
      "rating": 4
    },
    {
      "regionId": "madrid",
      "category": "city",
      "reason": "평균 9°C, 비가 거의 없는 맑은 날씨, 풍부한 일조량",
      "rating": 4
    },
    {
      "regionId": "barcelona",
      "category": "beach",
      "reason": "평균 11°C, 비가 거의 없는 맑은 날씨, 풍부한 일조량",
      "rating": 4
    },
    {
      "regionId": "venice",
      "category": "culture",
      "reason": "평균 7°C, 비가 거의 없는 맑은 날씨",
      "rating": 4
    },
    {
      "regionId": "amalfi",
      "category": "beach",
      "reason": "평균 11°C, 강수량 적음, 풍부한 일조량",
      "rating": 4
    },
    {
      "regionId": "edinburgh",
      "category": "culture",
      "reason": "평균 6°C, 강수량 적음",
      "rating": 4
    },
    {
      "regionId": "istanbul",
      "category": "culture",
      "reason": "평균 8°C, 강수량 적음",
      "rating": 4
    },
    {
      "regionId": "cappadocia",
      "category": "adventure",
      "reason": "평균 2°C, 비가 거의 없는 맑은 날씨, 풍부한 일조량",
      "rating": 4
    },
    {
      "regionId": "antalya",
      "category": "beach",
      "reason": "평균 11°C, 강수량 적음, 풍부한 일조량",
      "rating": 4
    },
    {
      "regionId": "santorini",
      "category": "beach",
      "reason": "평균 14°C, 비가 거의 없는 맑은 날씨, 풍부한 일조량",
      "rating": 4
    },
    {
      "regionId": "mykonos",
      "category": "beach",
      "reason": "평균 13°C, 비가 거의 없는 맑은 날씨, 풍부한 일조량",
      "rating": 4
    }
  ],
  "hiddenGems": [],
  "avoidList": [
    {
      "regionId": "osaka",
      "reason": "평균 6°C의 추위"
    },
    {
      "regionId": "paris",
      "reason": "평균 7°C의 추위"
    },
    {
      "regionId": "new-york",
      "reason": "평균 2°C의 혹한"
    },
    {
      "regionId": "hokkaido",
      "reason": "평균 -5°C의 혹한"
    }
  ]
}