{
  "month": 4,
  "bestDestinations": [
    {
      "regionId": "paris",
      "category": "culture",
      "reason": "평균 11°C, 강수량 적음, 풍부한 일조량",
      "rating": 5
    },
    {
      "regionId": "marseille",
      "category": "city",
      "reason": "평균 13°C, 비가 거의 없는 맑은 날씨, 풍부한 일조량",
      "rating": 5
    },
    {
      "regionId": "los-angeles",
      "category": "city",
      "reason": "평균 17°C의 온화한 날씨, 비가 거의 없는 맑은 날씨, 풍부한 일조량",
      "rating": 5
    },
    {
      "regionId": "hawaii",
      "category": "beach",
      "reason": "평균 23°C의 쾌적한 기온, 비가 거의 없는 맑은 날씨, 풍부한 일조량",
      "rating": 5
    },
    {
      "regionId": "san-francisco",
      "category": "city",
      "reason": "평균 12°C, 비가 거의 없는 맑은 날씨, 풍부한 일조량",
      "rating": 5
    },
    {
      "regionId": "las-vegas",
      "category": "city",
      "reason": "평균 21°C의 쾌적한 기온, 비가 거의 없는 맑은 날씨, 풍부한 일조량",
      "rating": 5
    },
    {
      "regionId": "kaohsiung",
      "category": "city",
      "reason": "평균 25°C의 쾌적한 기온, 강수량 적음, 풍부한 일조량",
      "rating": 5
    },
    {
      "regionId": "seville",
      "category": "culture",
      "reason": "평균 18°C의 온화한 날씨, 비가 거의 없는 맑은 날씨, 풍부한 일조량",
      "rating": 5
    },
    {
      "regionId": "antalya",
      "category": "beach",
      "reason": "평균 17°C의 온화한 날씨, 비가 거의 없는 맑은 날씨, 풍부한 일조량",
      "rating": 5
    },
    {
      "regionId": "santorini",
      "category": "beach",
      "reason": "평균 17°C의 온화한 날씨, 비가 거의 없는 맑은 날씨, 풍부한 일조량",
      "rating": 5
    },
    {
      "regionId": "mykonos",
      "category": "beach",
      "reason": "평균 17°C의 온화한 날씨, 비가 거의 없는 맑은 날씨, 풍부한 일조량",
      "rating": 5
    },
    {
      "regionId": "beijing",
      "category": "culture",
      "reason": "평균 15°C의 온화한 날씨, 비가 거의 없는 맑은 날씨, 풍부한 일조량",
      "rating": 5
    },
    {
      "regionId": "dubai",
      "category": "city",
      "reason": "평균 27°C의 쾌적한 기온, 비가 거의 없는 맑은 날씨, 풍부한 일조량",
      "rating": 5
    },
    {
      "regionId": "abu-dhabi",
      "category": "culture",
      "reason": "평균 28°C의 쾌적한 기온, 비가 거의 없는 맑은 날씨, 풍부한 일조량",
      "rating": 5
    },
    {
      "regionId": "new-delhi",
      "category": "culture",
      "reason": "평균 29°C의 온화한 날씨, 비가 거의 없는 맑은 날씨, 풍부한 일조량",
      "rating": 5
    },
    {
      "regionId": "mumbai",
      "category": "city",
      "reason": "평균 29°C의 온화한 날씨, 비가 거의 없는 맑은 날씨, 풍부한 일조량",
      "rating": 5
    },
    {
      "regionId": "cairo",
      "category": "culture",
      "reason": "평균 23°C의 쾌적한 기온, 비가 거의 없는 맑은 날씨, 풍부한 일조량",
      "rating": 5
    },
    {
      "regionId": "luxor",
      "category": "culture",
      "reason": "평균 27°C의 쾌적한 기온, 비가 거의 없는 맑은 날씨, 풍부한 일조량",
      "rating": 5
    },
    {
      "regionId": "marrakech",
      "category": "culture",
      "reason": "평균 20°C의 온화한 날씨, 비가 거의 없는 맑은 날씨, 풍부한 일조량",
      "rating": 5
    },
    {
      "regionId": "tokyo",
      "category": "city",
      "reason": "평균 14°C, 풍부한 일조량",
      "rating": 4
    },
    {
      "regionId": "osaka",
      "category": "culture",
      "reason": "평균 14°C, 풍부한 일조량",
      "rating": 4
    },
    {
      "regionId": "okinawa",
      "category": "beach",
      "reason": "평균 21°C의 쾌적한 기온, 풍부한 일조량",
      "rating": 4
    },
    {
      "regionId": "hokkaido",
      "category": "adventure",
      "reason": "평균 7°C, 강수량 적음, 풍부한 일조량",
      "rating": 4
    },
    {
      "regionId": "kyoto",
      "category": "culture",
      "reason": "평균 13°C, 풍부한 일조량",
      "rating": 4
    },
    {
      "regionId": "fukuoka",
      "category": "city",
      "reason": "평균 14°C, 풍부한 일조량",
      "rating": 4
    },
    {
      "regionId": "nagoya",
      "category": "city",
      "reason": "평균 14°C, 풍부한 일조량",
      "rating": 4
    },
    {
      "regionId": "hiroshima",
      "category": "culture",
      "reason": "평균 13°C, 풍부한 일조량",
      "rating": 4
    },
    {
      "regionId": "nara",
      "category": "culture",
      "reason": "평균 14°C, 풍부한 일조량",
      "rating": 4
    },
    {
      "regionId": "nagasaki",
      "category": "culture",
      "reason": "평균 16°C의 온화한 날씨, 풍부한 일조량",
      "rating": 4
    },
    {
      "regionId": "kobe",
      "category": "city",
      "reason": "평균 14°C, 풍부한 일조량",
      "rating": 4
    },
    {
      "regionId": "bangkok",
      "category": "culture",
      "reason": "평균 30°C의 온화한 날씨, 강수량 적음, 풍부한 일조량",
      "rating": 4
    },
    {
      "regionId": "chiang-mai",
      "category": "mountain",
      "reason": "평균 30°C의 온화한 날씨, 강수량 적음, 풍부한 일조량",
      "rating": 4
    },
    {
      "regionId": "phuket",
      "category": "beach",
      "reason": "평균 29°C의 온화한 날씨, 풍부한 일조량",
      "rating": 4
    },
    {
      "regionId": "pattaya",
      "category": "beach",
      "reason": "평균 30°C의 온화한 날씨, 강수량 적음, 풍부한 일조량",
      "rating": 4
    },
    {
      "regionId": "krabi",
      "category": "beach",
      "reason": "평균 29°C의 온화한 날씨, 풍부한 일조량",
      "rating": 4
    },
    {
      "regionId": "koh-samui",
      "category": "beach",
      "reason": "평균 29°C의 온화한 날씨, 강수량 적음, 풍부한 일조량",
      "rating": 4
    },
    {
      "regionId": "nice",
      "category": "beach",
      "reason": "평균 14°C, 비가 거의 없는 맑은 날씨, 풍부한 일조량",
      "rating": 4
    },
    {
      "regionId": "new-york",
      "category": "city",
      "reason": "평균 11°C, 풍부한 일조량",
      "rating": 4
    },
    {
      "regionId": "nha-trang",
      "category": "beach",
      "reason": "평균 28°C의 쾌적한 기온, 강수량 적음, 풍부한 일조량",
      "rating": 4
    },
    {
      "regionId": "hoi-an",
      "category": "culture",
      "reason": "평균 27°C의 쾌적한 기온, 강수량 적음, 풍부한 일조량",
      "rating": 4
    },
    {
      "regionId": "manila",
      "category": "city",
      "reason": "평균 29°C의 온화한 날씨, 강수량 적음, 풍부한 일조량",
      "rating": 4
    },
    {
      "regionId": "granada",
      "category": "culture",
      "reason": "평균 15°C, 강수량 적음, 풍부한 일조량",
      "rating": 4
    },
    {
      "regionId": "cappadocia",
      "category": "adventure",
      "reason": "평균 12°C, 비가 거의 없는 맑은 날씨, 풍부한 일조량",
      "rating": 4
    },
    {
      "regionId": "athens",
      "category": "culture",
      "reason": "평균 16°C의 온화한 날씨, 비가 거의 없는 맑은 날씨, 풍부한 일조량",
      "rating": 4
    },
    {
      "regionId": "xian",
      "category": "culture",
      "reason": "평균 17°C의 온화한 날씨, 강수량 적음",
      "rating": 4
    },
    {
      "regionId": "harbin",
      "category": "adventure",
      "reason": "평균 8°C, 비가 거의 없는 맑은 날씨, 풍부한 일조량",
      "rating": 4
    },
    {
      "regionId": "ulaanbaatar",
      "category": "adventure",
      "reason": "평균 3°C, 비가 거의 없는 맑은 날씨, 풍부한 일조량",
      "rating": 4
    },
    {
      "regionId": "luang-prabang",
      "category": "culture",
      "reason": "평균 28°C의 온화한 날씨, 강수량 적음, 풍부한 일조량",
      "rating": 4
    },
    {
      "regionId": "budapest",
      "category": "culture",
      "reason": "평균 11°C, 강수량 적음, 풍부한 일조량",
      "rating": 4
    },
    {
      "regionId": "cancun",
      "category": "beach",
      "reason": "평균 27°C의 쾌적한 기온, 비가 거의 없는 맑은 날씨, 풍부한 일조량",
      "rating": 4
    }
  ],
  "hiddenGems": [],
  "avoidList": [
    {
      "regionId": "cairns",
      "reason": "강수량 328mm의 우기"
    },
    {
      "regionId": "cebu",
      "reason": "잦은 비(156mm)"
    },
    {
      "regionId": "singapore",
      "reason": "강수량 288mm의 우기"
    },
    {
      "regionId": "bali",
      "reason": "잦은 비(163mm)"
    },
    {
      "regionId": "lombok",
      "reason": "잦은 비(150mm)"
    },
    {
      "regionId": "jakarta",
      "reason": "강수량 214mm의 우기"
    },
    {
      "regionId": "yogyakarta",
      "reason": "강수량 257mm의 우기"
    },
    {
      "regionId": "edinburgh",
      "reason": "평균 7°C의 추위"
    },
    {
      "regionId": "shanghai",
      "reason": "잦은 비(103mm)"
    },
    {
      "regionId": "zhangjiajie",
      "reason": "잦은 비(185mm)"
    },
    {
      "regionId": "hong-kong",
      "reason": "잦은 비(180mm)"
    },
    {
      "regionId": "kuala-lumpur",
      "reason": "강수량 262mm의 우기"
    },
    {
      "regionId": "kota-kinabalu",
      "reason": "잦은 비(167mm)"
    },
    {
      "regionId": "langkawi",
      "reason": "잦은 비(198mm)"
    },
    {
      "regionId": "penang",
      "reason": "강수량 356mm의 우기"
    },
    {
      "regionId": "zurich",
      "reason": "평균 9°C의 추위"
    },
    {
      "regionId": "interlaken",
      "reason": "잦은 비(144mm), 평균 10°C의 추위"
    },
    {
      "regionId": "queenstown",
      "reason": "잦은 비(110mm)"
    },
    {
      "regionId": "munich",
      "reason": "평균 8°C의 추위"
    },
    {
      "regionId": "vancouver",
      "reason": "잦은 비(111mm), 평균 8°C의 추위"
    },
    {
      "regionId": "toronto",
      "reason": "평균 7°C의 추위"
    },
    {
      "regionId": "salzburg",
      "reason": "잦은 비(103mm), 평균 9°C의 추위"
    },
    {
      "regionId": "colombo",
      "reason": "잦은 비(156mm)"
    },
    {
      "regionId": "guilin",
      "reason": "강수량 456mm의 우기"
    },
    {
      "regionId": "reykjavik",
      "reason": "잦은 비(130mm), 평균 4°C의 혹한"
    }
  ]
}