{"1":{"years":{"2022":[{"day":1,"tempHigh":9.2,"tempLow":3.7,"rainfall":0,"humidity":78},{"day":2,"tempHigh":9.9,"tempLow":3.3,"rainfall":0,"humidity":84},{"day":3,"tempHigh":12.1,"tempLow":7.2,"rainfall":1.5,"humidity":88},{"day":4,"tempHigh":12.7,"tempLow":9.6,"rainfall":4.3,"humidity":96},{"day":5,"tempHigh":13.3,"tempLow":10.1,"rainfall":0,"humidity":98},{"day":6,"tempHigh":11.6,"tempLow":9.2,"rainfall":0,"humidity":97},{"day":7,"tempHigh":12.3,"tempLow":8.1,"rainfall":1.4,"humidity":92},{"day":8,"tempHigh":12,"tempLow":6.7,"rainfall":0,"humidity":91},{"day":9,"tempHigh":12.9,"tempLow":6.8,"rainfall":0,"humidity":88},{"day":10,"tempHigh":15,"tempLow":7.4,"rainfall":0,"humidity":83},{"day":11,"tempHigh":14.9,"tempLow":6.9,"rainfall":0,"humidity":78},{"day":12,"tempHigh":13.1,"tempLow":6.8,"rainfall":0,"humidity":88},{"day":13,"tempHigh":14,"tempLow":8.2,"rainfall":0,"humidity":92},{"day":14,"tempHigh":12.9,"tempLow":6.7,"rainfall":0,"humidity":93},{"day":15,"tempHigh":15.6,"tempLow":9.4,"rainfall":0,"humidity":72},{"day":16,"tempHigh":13.7,"tempLow":9.1,"rainfall":0,"humidity":87},{"day":17,"tempHigh":14.1,"tempLow":7.3,"rainfall":0,"humidity":82},{"day":18,"tempHigh":11.6,"tempLow":7.7,"rainfall":0,"humidity":89},{"day":19,"tempHigh":11,"tempLow":7.8,"rainfall":0,"humidity":95},{"day":20,"tempHigh":16.1,"tempLow":7.7,"rainfall":0,"humidity":88},{"day":21,"tempHigh":18.9,"tempLow":7.4,"rainfall":0,"humidity":76},{"day":22,"tempHigh":18.4,"tempLow":8.8,"rainfall":0,"humidity":53},{"day":23,"tempHigh":15.2,"tempLow":6.8,"rainfall":0,"humidity":77},{"day":24,"tempHigh":11.7,"tempLow":7.8,"rainfall":0,"humidity":85},{"day":25,"tempHigh":12.2,"tempLow":7.5,"rainfall":0,"humidity":95},{"day":26,"tempHigh":14.6,"tempLow":6.7,"rainfall":0,"humidity":87},{"day":27,"tempHigh":15.6,"tempLow":6.2,"rainfall":0,"humidity":74},{"day":28,"tempHigh":16,"tempLow":6.8,"rainfall":0,"humidity":77},{"day":29,"tempHigh":15.5,"tempLow":7.5,"rainfall":0,"humidity":79},{"day":30,"tempHigh":10.9,"tempLow":7,"rainfall":0,"humidity":90},{"day":31,"tempHigh":12.9,"tempLow":7.8,"rainfall":0,"humidity":90}],"2023":[{"day":1,"tempHigh":15.2,"tempLow":7.6,"rainfall":0,"humidity":73},{"day":2,"tempHigh":10.6,"tempLow":7.1,"rainfall":23.8,"humidity":75},{"day":3,"tempHigh":12.8,"tempLow":6.2,"rainfall":4.2,"humidity":87},{"day":4,"tempHigh":14.2,"tempLow":7.9,"rainfall":37.8,"humidity":83},{"day":5,"tempHigh":12.9,"tempLow":8.4,"rainfall":10,"humidity":86},{"day":6,"tempHigh":14.5,"tempLow":9.2,"rainfall":0.1,"humidity":84},{"day":7,"tempHigh":12.8,"tempLow":10.8,"rainfall":12.1,"humidity":77},{"day":8,"tempHigh":14.9,"tempLow":10.9,"rainfall":21,"humidity":86},{"day":9,"tempHigh":14.2,"tempLow":9.5,"rainfall":37.8,"humidity":88},{"day":10,"tempHigh":12.9,"tempLow":9.4,"rainfall":18,"humidity":80},{"day":11,"tempHigh":13.4,"tempLow":9.4,"rainfall":29.7,"humidity":87},{"day":12,"tempHigh":15.9,"tempLow":11.4,"rainfall":0.1,"humidity":82},{"day":13,"tempHigh":13.8,"tempLow":11.2,"rainfall":10.2,"humidity":84},{"day":14,"tempHigh":13.8,"tempLow":10,"rainfall":24,"humidity":87},{"day":15,"tempHigh":11.8,"tempLow":9.6,"rainfall":12.8,"humidity":82},{"day":16,"tempHigh":11.6,"tempLow":7.6,"rainfall":15.3,"humidity":77},{"day":17,"tempHigh":11.8,"tempLow":4.6,"rainfall":0,"humidity":84},{"day":18,"tempHigh":11.8,"tempLow":6.8,"rainfall":1.5,"humidity":88},{"day":19,"tempHigh":11.6,"tempLow":4.8,"rainfall":2.1,"humidity":78},{"day":20,"tempHigh":11.6,"tempLow":6.1,"rainfall":0,"humidity":60},{"day":21,"tempHigh":11.8,"tempLow":4.2,"rainfall":0,"humidity":75},{"day":22,"tempHigh":14.4,"tempLow":5.9,"rainfall":0,"humidity":66},{"day":23,"tempHigh":15.3,"tempLow":7.7,"rainfall":0,"humidity":55},{"day":24,"tempHigh":14.8,"tempLow":6.2,"rainfall":0,"humidity":69},{"day":25,"tempHigh":16.1,"tempLow":5.3,"rainfall":0,"humidity":77},{"day":26,"tempHigh":16.3,"tempLow":8.1,"rainfall":0,"humidity":63},{"day":27,"tempHigh":11.4,"tempLow":7.4,"rainfall":0,"humidity":86},{"day":28,"tempHigh":11.2,"tempLow":6.4,"rainfall":0,"humidity":91},{"day":29,"tempHigh":9.1,"tempLow":7.5,"rainfall":0.7,"humidity":74},{"day":30,"tempHigh":11.2,"tempLow":3.3,"rainfall":0,"humidity":54},{"day":31,"tempHigh":12.8,"tempLow":3.3,"rainfall":0,"humidity":62}],"2024":[{"day":1,"tempHigh":14.5,"tempLow":7.4,"rainfall":0,"humidity":89},{"day":2,"tempHigh":15.4,"tempLow":8.1,"rainfall":14,"humidity":85},{"day":3,"tempHigh":13.5,"tempLow":8.6,"rainfall":2,"humidity":79},{"day":4,"tempHigh":14.7,"tempLow":6.8,"rainfall":0.3,"humidity":81},{"day":5,"tempHigh":15.8,"tempLow":8.5,"rainfall":0.5,"humidity":87},{"day":6,"tempHigh":13.1,"tempLow":7.5,"rainfall":4.1,"humidity":82},{"day":7,"tempHigh":11.9,"tempLow":4.7,"rainfall":0,"humidity":66},{"day":8,"tempHigh":11.1,"tempLow":4.5,"rainfall":0,"humidity":78},{"day":9,"tempHigh":13.9,"tempLow":8.7,"rainfall":6.5,"humidity":81},{"day":10,"tempHigh":12.7,"tempLow":7.9,"rainfall":3.8,"humidity":76},{"day":11,"tempHigh":11.7,"tempLow":4.6,"rainfall":0,"humidity":64},{"day":12,"tempHigh":12.1,"tempLow":4.8,"rainfall":0,"humidity":80},{"day":13,"tempHigh":13.2,"tempLow":8.4,"rainfall":12.7,"humidity":89},{"day":14,"tempHigh":14.1,"tempLow":8.2,"rainfall":0.4,"humidity":89},{"day":15,"tempHigh":14.1,"tempLow":7.9,"rainfall":0,"humidity":85},{"day":16,"tempHigh":12.9,"tempLow":7.4,"rainfall":13.7,"humidity":92},{"day":17,"tempHigh":14.6,"tempLow":8.7,"rainfall":0.4,"humidity":91},{"day":18,"tempHigh":15.2,"tempLow":7.8,"rainfall":0,"humidity":89},{"day":19,"tempHigh":13,"tempLow":8.6,"rainfall":13.1,"humidity":90},{"day":20,"tempHigh":14.7,"tempLow":12.1,"rainfall":10,"humidity":89},{"day":21,"tempHigh":16.1,"tempLow":11.7,"rainfall":9.5,"humidity":86},{"day":22,"tempHigh":14.6,"tempLow":11.8,"rainfall":17.7,"humidity":91},{"day":23,"tempHigh":15,"tempLow":10.9,"rainfall":0.5,"humidity":91},{"day":24,"tempHigh":15.3,"tempLow":11.2,"rainfall":6.1,"humidity":91},{"day":25,"tempHigh":14.6,"tempLow":9.2,"rainfall":0.3,"humidity":88},{"day":26,"tempHigh":16.9,"tempLow":8.9,"rainfall":0,"humidity":87},{"day":27,"tempHigh":16.8,"tempLow":10.4,"rainfall":0,"humidity":85},{"day":28,"tempHigh":20.4,"tempLow":10,"rainfall":0,"humidity":82},{"day":29,"tempHigh":19.4,"tempLow":9.3,"rainfall":0,"humidity":84},{"day":30,"tempHigh":15.9,"tempLow":10.3,"rainfall":0,"humidity":88},{"day":31,"tempHigh":14.8,"tempLow":12.8,"rainfall":38.4,"humidity":82}]}},"2":{"years":{"2022":[{"day":1,"tempHigh":15.3,"tempLow":5.1,"rainfall":0,"humidity":57},{"day":2,"tempHigh":15.6,"tempLow":8.8,"rainfall":0,"humidity":49},{"day":3,"tempHigh":13,"tempLow":7.4,"rainfall":0,"humidity":74},{"day":4,"tempHigh":15.6,"tempLow":6.9,"rainfall":0,"humidity":75},{"day":5,"tempHigh":14.3,"tempLow":7,"rainfall":0,"humidity":83},{"day":6,"tempHigh":17.1,"tempLow":5.8,"rainfall":0,"humidity":81},{"day":7,"tempHigh":18.2,"tempLow":6.7,"rainfall":0,"humidity":80},{"day":8,"tempHigh":17,"tempLow":7.7,"rainfall":0,"humidity":86},{"day":9,"tempHigh":20.3,"tempLow":7.9,"rainfall":0,"humidity":64},{"day":10,"tempHigh":21.5,"tempLow":10.6,"rainfall":0,"humidity":63},{"day":11,"tempHigh":22,"tempLow":10.1,"rainfall":0,"humidity":76},{"day":12,"tempHigh":21,"tempLow":10.4,"rainfall":0,"humidity":76},{"day":13,"tempHigh":20,"tempLow":7.9,"rainfall":0,"humidity":87},{"day":14,"tempHigh":12.5,"tempLow":10.1,"rainfall":0,"humidity":86},{"day":15,"tempHigh":14.9,"tempLow":7.4,"rainfall":0,"humidity":64},{"day":16,"tempHigh":18.1,"tempLow":8.4,"rainfall":0,"humidity":63},{"day":17,"tempHigh":17.8,"tempLow":7.7,"rainfall":0,"humidity":59},{"day":18,"tempHigh":17.4,"tempLow":9.8,"rainfall":0,"humidity":75},{"day":19,"tempHigh":18.1,"tempLow":7.2,"rainfall":0,"humidity":77},{"day":20,"tempHigh":12.6,"tempLow":9.2,"rainfall":0,"humidity":85},{"day":21,"tempHigh":12.2,"tempLow":6.8,"rainfall":1.8,"humidity":67},{"day":22,"tempHigh":10.2,"tempLow":5.5,"rainfall":2.1,"humidity":66},{"day":23,"tempHigh":11.4,"tempLow":5.2,"rainfall":0,"humidity":57},{"day":24,"tempHigh":10.1,"tempLow":4.5,"rainfall":0,"humidity":76},{"day":25,"tempHigh":13.1,"tempLow":4.4,"rainfall":0,"humidity":76},{"day":26,"tempHigh":14.1,"tempLow":5.1,"rainfall":0,"humidity":74},{"day":27,"tempHigh":17.4,"tempLow":7.3,"rainfall":0,"humidity":72},{"day":28,"tempHigh":17.2,"tempLow":7.8,"rainfall":0,"humidity":74}],"2023":[{"day":1,"tempHigh":12.1,"tempLow":4.1,"rainfall":0,"humidity":78},{"day":2,"tempHigh":11.8,"tempLow":4.1,"rainfall":0,"humidity":82},{"day":3,"tempHigh":11.3,"tempLow":8.8,"rainfall":13.4,"humidity":84},{"day":4,"tempHigh":14,"tempLow":7.8,"rainfall":9.4,"humidity":90},{"day":5,"tempHigh":11.5,"tempLow":8.1,"rainfall":8.4,"humidity":81},{"day":6,"tempHigh":13.2,"tempLow":5.2,"rainfall":0,"humidity":79},{"day":7,"tempHigh":13.8,"tempLow":6.2,"rainfall":0,"humidity":78},{"day":8,"tempHigh":14.6,"tempLow":5.7,"rainfall":0,"humidity":85},{"day":9,"tempHigh":15.7,"tempLow":5.7,"rainfall":0,"humidity":85},{"day":10,"tempHigh":12.1,"tempLow":8.6,"rainfall":0.1,"humidity":81},{"day":11,"tempHigh":12.1,"tempLow":5.6,"rainfall":5.1,"humidity":77},{"day":12,"tempHigh":13.6,"tempLow":6.6,"rainfall":0,"humidity":87},{"day":13,"tempHigh":14.3,"tempLow":6.7,"rainfall":0,"humidity":85},{"day":14,"tempHigh":10.1,"tempLow":6.3,"rainfall":0.2,"humidity":62},{"day":15,"tempHigh":12.6,"tempLow":5.1,"rainfall":0,"humidity":59},{"day":16,"tempHigh":11.2,"tempLow":4.7,"rainfall":0,"humidity":74},{"day":17,"tempHigh":14.8,"tempLow":5.8,"rainfall":0,"humidity":67},{"day":18,"tempHigh":14.1,"tempLow":4.9,"rainfall":0,"humidity":73},{"day":19,"tempHigh":12.4,"tempLow":5.6,"rainfall":0,"humidity":82},{"day":20,"tempHigh":16,"tempLow":5.9,"rainfall":0,"humidity":84},{"day":21,"tempHigh":11.4,"tempLow":6.8,"rainfall":0,"humidity":77},{"day":22,"tempHigh":8.7,"tempLow":5.8,"rainfall":0.4,"humidity":66},{"day":23,"tempHigh":8.2,"tempLow":4.7,"rainfall":3.5,"humidity":71},{"day":24,"tempHigh":7.9,"tempLow":5,"rainfall":15,"humidity":79},{"day":25,"tempHigh":8.7,"tempLow":4.7,"rainfall":0.5,"humidity":80},{"day":26,"tempHigh":9.7,"tempLow":5.8,"rainfall":8.6,"humidity":83},{"day":27,"tempHigh":9.4,"tempLow":5.2,"rainfall":11.1,"humidity":74},{"day":28,"tempHigh":10,"tempLow":6.3,"rainfall":12.7,"humidity":80}],"2024":[{"day":1,"tempHigh":13.4,"tempLow":10.5,"rainfall":15.6,"humidity":86},{"day":2,"tempHigh":12.6,"tempLow":8.9,"rainfall":4.8,"humidity":77},{"day":3,"tempHigh":12.2,"tempLow":8.3,"rainfall":8.3,"humidity":79},{"day":4,"tempHigh":15.2,"tempLow":9.8,"rainfall":37.3,"humidity":80},{"day":5,"tempHigh":13.4,"tempLow":9.7,"rainfall":8.2,"humidity":80},{"day":6,"tempHigh":12.9,"tempLow":7.5,"rainfall":0.7,"humidity":85},{"day":7,"tempHigh":11.8,"tempLow":7.9,"rainfall":7.4,"humidity":72},{"day":8,"tempHigh":13.1,"tempLow":4.7,"rainfall":0.1,"humidity":75},{"day":9,"tempHigh":12.1,"tempLow":5.8,"rainfall":0,"humidity":84},{"day":10,"tempHigh":15.5,"tempLow":5.9,"rainfall":0,"humidity":78},{"day":11,"tempHigh":14.1,"tempLow":7.7,"rainfall":0,"humidity":89},{"day":12,"tempHigh":13.9,"tempLow":7.1,"rainfall":0,"humidity":88},{"day":13,"tempHigh":13.9,"tempLow":8.1,"rainfall":0.2,"humidity":87},{"day":14,"tempHigh":14.3,"tempLow":9.8,"rainfall":10.6,"humidity":88},{"day":15,"tempHigh":15.1,"tempLow":9.9,"rainfall":1,"humidity":87},{"day":16,"tempHigh":15.9,"tempLow":9.4,"rainfall":0,"humidity":88},{"day":17,"tempHigh":14.6,"tempLow":10.1,"rainfall":26.7,"humidity":88},{"day":18,"tempHigh":18.2,"tempLow":11,"rainfall":16.3,"humidity":86},{"day":19,"tempHigh":14.9,"tempLow":11.8,"rainfall":11.9,"humidity":84},{"day":20,"tempHigh":14,"tempLow":9.6,"rainfall":12.3,"humidity":87},{"day":21,"tempHigh":13.5,"tempLow":8.6,"rainfall":1.2,"humidity":88},{"day":22,"tempHigh":15.2,"tempLow":8.3,"rainfall":0,"humidity":86},{"day":23,"tempHigh":17.5,"tempLow":7.5,"rainfall":0,"humidity":77},{"day":24,"tempHigh":20.5,"tempLow":8,"rainfall":0,"humidity":75},{"day":25,"tempHigh":15.1,"tempLow":8.6,"rainfall":0,"humidity":88},{"day":26,"tempHigh":15.2,"tempLow":9.4,"rainfall":0.1,"humidity":86},{"day":27,"tempHigh":14.1,"tempLow":6.6,"rainfall":0,"humidity":73},{"day":28,"tempHigh":15.7,"tempLow":6.8,"rainfall":0,"humidity":82},{"day":29,"tempHigh":14,"tempLow":11.2,"rainfall":7.3,"humidity":84}]}},"3":{"years":{"2022":[{"day":1,"tempHigh":13.2,"tempLow":8.8,"rainfall":0,"humidity":93},{"day":2,"tempHigh":12.9,"tempLow":10.2,"rainfall":0,"humidity":95},{"day":3,"tempHigh":13,"tempLow":9.8,"rainfall":4.1,"humidity":90},{"day":4,"tempHigh":12.9,"tempLow":7.9,"rainfall":2.2,"humidity":79},{"day":5,"tempHigh":12.3,"tempLow":6.7,"rainfall":0,"humidity":70},{"day":6,"tempHigh":12.4,"tempLow":6.3,"rainfall":0,"humidity":82},{"day":7,"tempHigh":18.9,"tempLow":6.5,"rainfall":0,"humidity":68},{"day":8,"tempHigh":15.9,"tempLow":7,"rainfall":0,"humidity":67},{"day":9,"tempHigh":14.6,"tempLow":7.6,"rainfall":0,"humidity":74},{"day":10,"tempHigh":18.5,"tempLow":7.9,"rainfall":0,"humidity":58},{"day":11,"tempHigh":17.3,"tempLow":9.1,"rainfall":0,"humidity":62},{"day":12,"tempHigh":11.9,"tempLow":6.8,"rainfall":0,"humidity":84},{"day":13,"tempHigh":12.9,"tempLow":9.6,"rainfall":1.1,"humidity":80},{"day":14,"tempHigh":14.1,"tempLow":7.2,"rainfall":0,"humidity":81},{"day":15,"tempHigh":14.9,"tempLow":11.6,"rainfall":4.1,"humidity":89},{"day":16,"tempHigh":14.6,"tempLow":9.3,"rainfall":0,"humidity":80},{"day":17,"tempHigh":12.8,"tempLow":10,"rainfall":0,"humidity":82},{"day":18,"tempHigh":12.7,"tempLow":8.5,"rainfall":0,"humidity":85},{"day":19,"tempHigh":12.5,"tempLow":9.8,"rainfall":4,"humidity":83},{"day":20,"tempHigh":14.9,"tempLow":7.4,"rainfall":0,"humidity":74},{"day":21,"tempHigh":17.2,"tempLow":8.4,"rainfall":0,"humidity":74},{"day":22,"tempHigh":19.9,"tempLow":11,"rainfall":0,"humidity":82},{"day":23,"tempHigh":16.7,"tempLow":10.7,"rainfall":0,"humidity":88},{"day":24,"tempHigh":12.8,"tempLow":9.4,"rainfall":0,"humidity":87},{"day":25,"tempHigh":14.4,"tempLow":9.4,"rainfall":0,"humidity":82},{"day":26,"tempHigh":13.1,"tempLow":9.1,"rainfall":0,"humidity":89},{"day":27,"tempHigh":15.9,"tempLow":10.1,"rainfall":10.3,"humidity":81},{"day":28,"tempHigh":14.1,"tempLow":10.8,"rainfall":6.6,"humidity":82},{"day":29,"tempHigh":14.4,"tempLow":9.9,"rainfall":0,"humidity":87},{"day":30,"tempHigh":14.1,"tempLow":9.8,"rainfall":0,"humidity":82},{"day":31,"tempHigh":14.1,"tempLow":10.2,"rainfall":0,"humidity":82}],"2023":[{"day":1,"tempHigh":12.4,"tempLow":4.2,"rainfall":0,"humidity":63},{"day":2,"tempHigh":11.1,"tempLow":5.7,"rainfall":0,"humidity":71},{"day":3,"tempHigh":10.6,"tempLow":6.3,"rainfall":0,"humidity":83},{"day":4,"tempHigh":9.8,"tempLow":7.2,"rainfall":3.5,"humidity":72},{"day":5,"tempHigh":9.4,"tempLow":6.7,"rainfall":4.7,"humidity":69},{"day":6,"tempHigh":9.9,"tempLow":5.2,"rainfall":4.6,"humidity":78},{"day":7,"tempHigh":10,"tempLow":5.9,"rainfall":2.2,"humidity":73},{"day":8,"tempHigh":9.9,"tempLow":6.8,"rainfall":6.5,"humidity":74},{"day":9,"tempHigh":12.2,"tempLow":5.6,"rainfall":39.7,"humidity":83},{"day":10,"tempHigh":12.6,"tempLow":7.8,"rainfall":24.4,"humidity":85},{"day":11,"tempHigh":13.6,"tempLow":6.8,"rainfall":8.5,"humidity":91},{"day":12,"tempHigh":14.8,"tempLow":11.2,"rainfall":11.6,"humidity":92},{"day":13,"tempHigh":15.8,"tempLow":11.4,"rainfall":5.7,"humidity":92},{"day":14,"tempHigh":14.2,"tempLow":8.8,"rainfall":27.8,"humidity":88},{"day":15,"tempHigh":12.6,"tempLow":6.7,"rainfall":0,"humidity":76},{"day":16,"tempHigh":12.3,"tempLow":7.2,"rainfall":0,"humidity":86},{"day":17,"tempHigh":14.9,"tempLow":7.4,"rainfall":0,"humidity":83},{"day":18,"tempHigh":17.5,"tempLow":8.1,"rainfall":0,"humidity":84},{"day":19,"tempHigh":13.4,"tempLow":10.6,"rainfall":22.3,"humidity":88},{"day":20,"tempHigh":10.9,"tempLow":8.6,"rainfall":0.4,"humidity":75},{"day":21,"tempHigh":12.4,"tempLow":8.6,"rainfall":31.9,"humidity":80},{"day":22,"tempHigh":12.6,"tempLow":8.7,"rainfall":9.5,"humidity":79},{"day":23,"tempHigh":11.9,"tempLow":9.1,"rainfall":0.1,"humidity":76},{"day":24,"tempHigh":13.1,"tempLow":7,"rainfall":0,"humidity":66},{"day":25,"tempHigh":12.6,"tempLow":6.2,"rainfall":0,"humidity":67},{"day":26,"tempHigh":11.1,"tempLow":5.9,"rainfall":0,"humidity":64},{"day":27,"tempHigh":11.7,"tempLow":6.4,"rainfall":0,"humidity":70},{"day":28,"tempHigh":11.2,"tempLow":8.4,"rainfall":17.1,"humidity":77},{"day":29,"tempHigh":10.1,"tempLow":7.8,"rainfall":8.3,"humidity":81},{"day":30,"tempHigh":11.1,"tempLow":5.5,"rainfall":0.5,"humidity":80},{"day":31,"tempHigh":12,"tempLow":7.8,"rainfall":0,"humidity":78}],"2024":[{"day":1,"tempHigh":12.5,"tempLow":10.1,"rainfall":12.4,"humidity":79},{"day":2,"tempHigh":10.6,"tempLow":8.2,"rainfall":10.3,"humidity":70},{"day":3,"tempHigh":12.1,"tempLow":8.4,"rainfall":3.7,"humidity":70},{"day":4,"tempHigh":13.5,"tempLow":7.2,"rainfall":0.1,"humidity":75},{"day":5,"tempHigh":15.1,"tempLow":10.7,"rainfall":2.2,"humidity":81},{"day":6,"tempHigh":13.9,"tempLow":10.1,"rainfall":21.9,"humidity":88},{"day":7,"tempHigh":15.4,"tempLow":6.9,"rainfall":0,"humidity":83},{"day":8,"tempHigh":15.8,"tempLow":7.1,"rainfall":0,"humidity":82},{"day":9,"tempHigh":14.5,"tempLow":8.4,"rainfall":0,"humidity":83},{"day":10,"tempHigh":14.4,"tempLow":9,"rainfall":6.7,"humidity":77},{"day":11,"tempHigh":13.1,"tempLow":8.2,"rainfall":7.6,"humidity":77},{"day":12,"tempHigh":14.6,"tempLow":10.9,"rainfall":5.2,"humidity":80},{"day":13,"tempHigh":16.4,"tempLow":7,"rainfall":0,"humidity":72},{"day":14,"tempHigh":18,"tempLow":11.2,"rainfall":0,"humidity":43},{"day":15,"tempHigh":21,"tempLow":12.2,"rainfall":0,"humidity":44},{"day":16,"tempHigh":17.5,"tempLow":9.6,"rainfall":0,"humidity":78},{"day":17,"tempHigh":16.2,"tempLow":10.1,"rainfall":0,"humidity":85},{"day":18,"tempHigh":16.2,"tempLow":10.8,"rainfall":0,"humidity":87},{"day":19,"tempHigh":14.8,"tempLow":11.1,"rainfall":0,"humidity":84},{"day":20,"tempHigh":15.3,"tempLow":8.7,"rainfall":0,"humidity":82},{"day":21,"tempHigh":16.3,"tempLow":9.9,"rainfall":0,"humidity":85},{"day":22,"tempHigh":17.5,"tempLow":10.9,"rainfall":11.1,"humidity":84},{"day":23,"tempHigh":13.2,"tempLow":10.1,"rainfall":13.8,"humidity":79},{"day":24,"tempHigh":15,"tempLow":10.1,"rainfall":0.6,"humidity":75},{"day":25,"tempHigh":14.1,"tempLow":9.6,"rainfall":0,"humidity":77},{"day":26,"tempHigh":14.9,"tempLow":9.6,"rainfall":0,"humidity":78},{"day":27,"tempHigh":14.4,"tempLow":9.9,"rainfall":7.3,"humidity":84},{"day":28,"tempHigh":13.9,"tempLow":9.9,"rainfall":0.7,"humidity":73},{"day":29,"tempHigh":12.6,"tempLow":9.4,"rainfall":20.3,"humidity":82},{"day":30,"tempHigh":15.5,"tempLow":9.6,"rainfall":1.4,"humidity":74},{"day":31,"tempHigh":15.6,"tempLow":8.4,"rainfall":0.2,"humidity":84}]}},"4":{"years":{"2022":[{"day":1,"tempHigh":15.1,"tempLow":9.4,"rainfall":0,"humidity":83},{"day":2,"tempHigh":16.6,"tempLow":9.9,"rainfall":0,"humidity":78},{"day":3,"tempHigh":16.2,"tempLow":9.1,"rainfall":0,"humidity":78},{"day":4,"tempHigh":14.6,"tempLow":10.4,"rainfall":0,"humidity":81},{"day":5,"tempHigh":16.5,"tempLow":9.6,"rainfall":0,"humidity":74},{"day":6,"tempHigh":22.8,"tempLow":11.1,"rainfall":0,"humidity":69},{"day":7,"tempHigh":29,"tempLow":11.4,"rainfall":0,"humidity":61},{"day":8,"tempHigh":21.2,"tempLow":11.4,"rainfall":0,"humidity":75},{"day":9,"tempHigh":18.8,"tempLow":8.9,"rainfall":0,"humidity":68},{"day":10,"tempHigh":16.7,"tempLow":9.9,"rainfall":0,"humidity":59},{"day":11,"tempHigh":11.9,"tempLow":8.9,"rainfall":3.1,"humidity":68},{"day":12,"tempHigh":11.6,"tempLow":7.6,"rainfall":0,"humidity":63},{"day":13,"tempHigh":11.8,"tempLow":7.6,"rainfall":0,"humidity":70},{"day":14,"tempHigh":13.4,"tempLow":10.9,"rainfall":13.4,"humidity":85},{"day":15,"tempHigh":11.9,"tempLow":8.1,"rainfall":0,"humidity":74},{"day":16,"tempHigh":13.5,"tempLow":9,"rainfall":15.6,"humidity":82},{"day":17,"tempHigh":12.1,"tempLow":8.2,"rainfall":0,"humidity":78},{"day":18,"tempHigh":16.2,"tempLow":7.7,"rainfall":0.7,"humidity":79},{"day":19,"tempHigh":14,"tempLow":10.9,"rainfall":1.5,"humidity":84},{"day":20,"tempHigh":16.2,"tempLow":10.2,"rainfall":11.2,"humidity":79},{"day":21,"tempHigh":14,"tempLow":10.9,"rainfall":9.3,"humidity":82},{"day":22,"tempHigh":13.2,"tempLow":10.3,"rainfall":8.8,"humidity":80},{"day":23,"tempHigh":16.4,"tempLow":9,"rainfall":0,"humidity":83},{"day":24,"tempHigh":16.6,"tempLow":9.3,"rainfall":0,"humidity":83},{"day":25,"tempHigh":16.5,"tempLow":9.8,"rainfall":0,"humidity":82},{"day":26,"tempHigh":15.4,"tempLow":10.9,"rainfall":0,"humidity":76},{"day":27,"tempHigh":15.1,"tempLow":9.3,"rainfall":0,"humidity":74},{"day":28,"tempHigh":14.1,"tempLow":9.9,"rainfall":0,"humidity":70},{"day":29,"tempHigh":16.4,"tempLow":8.9,"rainfall":0,"humidity":72},{"day":30,"tempHigh":17,"tempLow":10.6,"rainfall":0,"humidity":79}],"2023":[{"day":1,"tempHigh":12.8,"tempLow":6.8,"rainfall":0,"humidity":80},{"day":2,"tempHigh":12.1,"tempLow":8.3,"rainfall":0.1,"humidity":76},{"day":3,"tempHigh":11.9,"tempLow":6.6,"rainfall":0.1,"humidity":62},{"day":4,"tempHigh":11.8,"tempLow":4.8,"rainfall":0,"humidity":66},{"day":5,"tempHigh":11.2,"tempLow":6.3,"rainfall":0,"humidity":78},{"day":6,"tempHigh":11.7,"tempLow":6.9,"rainfall":0,"humidity":83},{"day":7,"tempHigh":13.2,"tempLow":9.8,"rainfall":2.9,"humidity":86},{"day":8,"tempHigh":14.4,"tempLow":9.4,"rainfall":0,"humidity":81},{"day":9,"tempHigh":16.3,"tempLow":9.4,"rainfall":0,"humidity":79},{"day":10,"tempHigh":13.4,"tempLow":10.1,"rainfall":0.1,"humidity":95},{"day":11,"tempHigh":14.7,"tempLow":9.3,"rainfall":0,"humidity":84},{"day":12,"tempHigh":13.8,"tempLow":8.2,"rainfall":0,"humidity":69},{"day":13,"tempHigh":13.8,"tempLow":7.7,"rainfall":0,"humidity":67},{"day":14,"tempHigh":12.1,"tempLow":7.7,"rainfall":0,"humidity":81},{"day":15,"tempHigh":11.8,"tempLow":8.6,"rainfall":0,"humidity":81},{"day":16,"tempHigh":12.3,"tempLow":8.2,"rainfall":0,"humidity":79},{"day":17,"tempHigh":11.8,"tempLow":9.4,"rainfall":0,"humidity":78},{"day":18,"tempHigh":11,"tempLow":8.6,"rainfall":0.4,"humidity":70},{"day":19,"tempHigh":13.6,"tempLow":8.3,"rainfall":0.1,"humidity":70},{"day":20,"tempHigh":15.7,"tempLow":7.8,"rainfall":0,"humidity":73},{"day":21,"tempHigh":19,"tempLow":10.4,"rainfall":0,"humidity":80},{"day":22,"tempHigh":16.8,"tempLow":10.9,"rainfall":0,"humidity":87},{"day":23,"tempHigh":16.6,"tempLow":10.8,"rainfall":0,"humidity":85},{"day":24,"tempHigh":16.2,"tempLow":9.8,"rainfall":0,"humidity":77},{"day":25,"tempHigh":16,"tempLow":8.9,"rainfall":0,"humidity":85},{"day":26,"tempHigh":13.6,"tempLow":9.8,"rainfall":0,"humidity":93},{"day":27,"tempHigh":16.4,"tempLow":10.2,"rainfall":0,"humidity":93},{"day":28,"tempHigh":12.5,"tempLow":9.7,"rainfall":0,"humidity":93},{"day":29,"tempHigh":12.9,"tempLow":9,"rainfall":0,"humidity":91},{"day":30,"tempHigh":14.7,"tempLow":10.3,"rainfall":0,"humidity":79}],"2024":[{"day":1,"tempHigh":17.9,"tempLow":8.3,"rainfall":0,"humidity":80},{"day":2,"tempHigh":15.2,"tempLow":9.7,"rainfall":0,"humidity":90},{"day":3,"tempHigh":14.4,"tempLow":10.1,"rainfall":0,"humidity":81},{"day":4,"tempHigh":10.8,"tempLow":6.8,"rainfall":7.7,"humidity":68},{"day":5,"tempHigh":12.9,"tempLow":5.8,"rainfall":0.3,"humidity":71},{"day":6,"tempHigh":12.9,"tempLow":6.2,"rainfall":0,"humidity":69},{"day":7,"tempHigh":15.3,"tempLow":7.4,"rainfall":0.8,"humidity":71},{"day":8,"tempHigh":18.1,"tempLow":7.4,"rainfall":0,"humidity":71},{"day":9,"tempHigh":16.2,"tempLow":9.4,"rainfall":0,"humidity":87},{"day":10,"tempHigh":22.6,"tempLow":9.6,"rainfall":0,"humidity":84},{"day":11,"tempHigh":19,"tempLow":10.2,"rainfall":0,"humidity":82},{"day":12,"tempHigh":14.4,"tempLow":10.4,"rainfall":0.3,"humidity":78},{"day":13,"tempHigh":12.9,"tempLow":8.6,"rainfall":14.6,"humidity":76},{"day":14,"tempHigh":14.1,"tempLow":7.3,"rainfall":3.2,"humidity":79},{"day":15,"tempHigh":15,"tempLow":8.2,"rainfall":0.2,"humidity":85},{"day":16,"tempHigh":17.8,"tempLow":9.4,"rainfall":0,"humidity":86},{"day":17,"tempHigh":21.4,"tempLow":9.5,"rainfall":0,"humidity":82},{"day":18,"tempHigh":20.4,"tempLow":9.9,"rainfall":0,"humidity":88},{"day":19,"tempHigh":14.4,"tempLow":10.6,"rainfall":0,"humidity":88},{"day":20,"tempHigh":19,"tempLow":10.9,"rainfall":0,"humidity":73},{"day":21,"tempHigh":18.6,"tempLow":10.1,"rainfall":0,"humidity":82},{"day":22,"tempHigh":18.2,"tempLow":10.6,"rainfall":0,"humidity":85},{"day":23,"tempHigh":17.1,"tempLow":12.2,"rainfall":0.4,"humidity":74},{"day":24,"tempHigh":16.2,"tempLow":11.1,"rainfall":0.1,"humidity":78},{"day":25,"tempHigh":15.9,"tempLow":10.8,"rainfall":0,"humidity":80},{"day":26,"tempHigh":16.1,"tempLow":11.3,"rainfall":0,"humidity":79},{"day":27,"tempHigh":17.2,"tempLow":9.6,"rainfall":0,"humidity":72},{"day":28,"tempHigh":19.1,"tempLow":10.2,"rainfall":0,"humidity":70},{"day":29,"tempHigh":19.8,"tempLow":9.1,"rainfall":0,"humidity":65},{"day":30,"tempHigh":19,"tempLow":8,"rainfall":0,"humidity":66}]}},"5":{"years":{"2022":[{"day":1,"tempHigh":16.2,"tempLow":8.9,"rainfall":0,"humidity":73},{"day":2,"tempHigh":15.4,"tempLow":10.2,"rainfall":0,"humidity":74},{"day":3,"tempHigh":20,"tempLow":9.1,"rainfall":0,"humidity":63},{"day":4,"tempHigh":17.9,"tempLow":10.1,"rainfall":0,"humidity":84},{"day":5,"tempHigh":13.5,"tempLow":10.7,"rainfall":0.4,"humidity":85},{"day":6,"tempHigh":16.1,"tempLow":12.1,"rainfall":1.4,"humidity":91},{"day":7,"tempHigh":15.8,"tempLow":10.6,"rainfall":0,"humidity":76},{"day":8,"tempHigh":13.3,"tempLow":9.6,"rainfall":0,"humidity":65},{"day":9,"tempHigh":11.8,"tempLow":9.2,"rainfall":0.1,"humidity":67},{"day":10,"tempHigh":12.2,"tempLow":8.6,"rainfall":1.2,"humidity":67},{"day":11,"tempHigh":15.1,"tempLow":7.2,"rainfall":0,"humidity":71},{"day":12,"tempHigh":14.1,"tempLow":9.3,"rainfall":0,"humidity":71},{"day":13,"tempHigh":19.6,"tempLow":10.6,"rainfall":0,"humidity":75},{"day":14,"tempHigh":19.5,"tempLow":11.4,"rainfall":0,"humidity":78},{"day":15,"tempHigh":17.9,"tempLow":11.9,"rainfall":0,"humidity":84},{"day":16,"tempHigh":15.6,"tempLow":11.6,"rainfall":0,"humidity":82},{"day":17,"tempHigh":18.5,"tempLow":10.6,"rainfall":0,"humidity":73},{"day":18,"tempHigh":24.8,"tempLow":10.8,"rainfall":0,"humidity":66},{"day":19,"tempHigh":20.7,"tempLow":13.9,"rainfall":0,"humidity":60},{"day":20,"tempHigh":21.8,"tempLow":12.2,"rainfall":0,"humidity":47},{"day":21,"tempHigh":17,"tempLow":11.4,"rainfall":0,"humidity":73},{"day":22,"tempHigh":19.4,"tempLow":10.4,"rainfall":0,"humidity":70},{"day":23,"tempHigh":20.5,"tempLow":12.8,"rainfall":0,"humidity":64},{"day":24,"tempHigh":21.5,"tempLow":12.1,"rainfall":0,"humidity":68},{"day":25,"tempHigh":20.6,"tempLow":11.8,"rainfall":0,"humidity":73},{"day":26,"tempHigh":15.6,"tempLow":11.1,"rainfall":0,"humidity":86},{"day":27,"tempHigh":14.9,"tempLow":11.9,"rainfall":0.1,"humidity":88},{"day":28,"tempHigh":14.1,"tempLow":12.2,"rainfall":0.2,"humidity":87},{"day":29,"tempHigh":18.8,"tempLow":11.2,"rainfall":0,"humidity":67},{"day":30,"tempHigh":18.2,"tempLow":10.6,"rainfall":0,"humidity":65},{"day":31,"tempHigh":21.2,"tempLow":10.7,"rainfall":0,"humidity":65}],"2023":[{"day":1,"tempHigh":12.7,"tempLow":10.1,"rainfall":1.4,"humidity":78},{"day":2,"tempHigh":12.6,"tempLow":9.2,"rainfall":8.8,"humidity":76},{"day":3,"tempHigh":13.9,"tempLow":10.9,"rainfall":16.1,"humidity":77},{"day":4,"tempHigh":12.9,"tempLow":10.4,"rainfall":0.1,"humidity":83},{"day":5,"tempHigh":13.9,"tempLow":10.4,"rainfall":2.2,"humidity":81},{"day":6,"tempHigh":14.1,"tempLow":11.1,"rainfall":0.9,"humidity":83},{"day":7,"tempHigh":13.6,"tempLow":9.2,"rainfall":0,"humidity":80},{"day":8,"tempHigh":13.9,"tempLow":10.7,"rainfall":1.8,"humidity":78},{"day":9,"tempHigh":14,"tempLow":9.9,"rainfall":0,"humidity":84},{"day":10,"tempHigh":13.4,"tempLow":11.1,"rainfall":0.3,"humidity":78},{"day":11,"tempHigh":15.1,"tempLow":11.2,"rainfall":0,"humidity":82},{"day":12,"tempHigh":16.6,"tempLow":11.1,"rainfall":0,"humidity":85},{"day":13,"tempHigh":19,"tempLow":12.4,"rainfall":0,"humidity":88},{"day":14,"tempHigh":17.2,"tempLow":12.3,"rainfall":0,"humidity":87},{"day":15,"tempHigh":15.3,"tempLow":12.4,"rainfall":0,"humidity":88},{"day":16,"tempHigh":17,"tempLow":12.1,"rainfall":0,"humidity":86},{"day":17,"tempHigh":15.6,"tempLow":11.9,"rainfall":0,"humidity":86},{"day":18,"tempHigh":16.3,"tempLow":11.1,"rainfall":0,"humidity":85},{"day":19,"tempHigh":16.1,"tempLow":11.9,"rainfall":0,"humidity":84},{"day":20,"tempHigh":14.6,"tempLow":11.6,"rainfall":0,"humidity":86},{"day":21,"tempHigh":15.1,"tempLow":11.5,"rainfall":0,"humidity":88},{"day":22,"tempHigh":15.6,"tempLow":12,"rainfall":0,"humidity":87},{"day":23,"tempHigh":16.7,"tempLow":11.4,"rainfall":0,"humidity":80},{"day":24,"tempHigh":16.4,"tempLow":11.3,"rainfall":0,"humidity":78},{"day":25,"tempHigh":15.2,"tempLow":11.9,"rainfall":0,"humidity":79},{"day":26,"tempHigh":15.1,"tempLow":12.1,"rainfall":0.1,"humidity":80},{"day":27,"tempHigh":14.6,"tempLow":12.1,"rainfall":0,"humidity":83},{"day":28,"tempHigh":14.6,"tempLow":12,"rainfall":0,"humidity":85},{"day":29,"tempHigh":16.1,"tempLow":12.2,"rainfall":0,"humidity":78},{"day":30,"tempHigh":15.9,"tempLow":12.7,"rainfall":0,"humidity":78},{"day":31,"tempHigh":14.6,"tempLow":11.6,"rainfall":0,"humidity":81}],"2024":[{"day":1,"tempHigh":22,"tempLow":8.9,"rainfall":0,"humidity":63},{"day":2,"tempHigh":21.1,"tempLow":10.4,"rainfall":0,"humidity":67},{"day":3,"tempHigh":19.4,"tempLow":10.1,"rainfall":0,"humidity":74},{"day":4,"tempHigh":12.6,"tempLow":9.4,"rainfall":20.8,"humidity":83},{"day":5,"tempHigh":13.8,"tempLow":8.6,"rainfall":0,"humidity":71},{"day":6,"tempHigh":14.2,"tempLow":9,"rainfall":0,"humidity":79},{"day":7,"tempHigh":17,"tempLow":8.8,"rainfall":0,"humidity":75},{"day":8,"tempHigh":25.5,"tempLow":9.9,"rainfall":0,"humidity":42},{"day":9,"tempHigh":28.3,"tempLow":13.6,"rainfall":0,"humidity":45},{"day":10,"tempHigh":22,"tempLow":10.4,"rainfall":0,"humidity":68},{"day":11,"tempHigh":19.7,"tempLow":11.9,"rainfall":0,"humidity":77},{"day":12,"tempHigh":16.3,"tempLow":11.1,"rainfall":0,"humidity":83},{"day":13,"tempHigh":15.4,"tempLow":10.8,"rainfall":0,"humidity":83},{"day":14,"tempHigh":15.9,"tempLow":10.2,"rainfall":0,"humidity":87},{"day":15,"tempHigh":16.2,"tempLow":10.9,"rainfall":0,"humidity":86},{"day":16,"tempHigh":16.9,"tempLow":12,"rainfall":0,"humidity":85},{"day":17,"tempHigh":17.3,"tempLow":11.5,"rainfall":0,"humidity":79},{"day":18,"tempHigh":16.7,"tempLow":11.1,"rainfall":0,"humidity":81},{"day":19,"tempHigh":18.1,"tempLow":9.6,"rainfall":0,"humidity":71},{"day":20,"tempHigh":18,"tempLow":9.1,"rainfall":0,"humidity":73},{"day":21,"tempHigh":22.5,"tempLow":9.9,"rainfall":0,"humidity":68},{"day":22,"tempHigh":22.4,"tempLow":10.6,"rainfall":0,"humidity":67},{"day":23,"tempHigh":19.5,"tempLow":10.4,"rainfall":0,"humidity":62},{"day":24,"tempHigh":14.6,"tempLow":10.1,"rainfall":0,"humidity":77},{"day":25,"tempHigh":15.2,"tempLow":10.6,"rainfall":0,"humidity":78},{"day":26,"tempHigh":17.9,"tempLow":9.7,"rainfall":0,"humidity":74},{"day":27,"tempHigh":15.5,"tempLow":10.2,"rainfall":0,"humidity":79},{"day":28,"tempHigh":19.7,"tempLow":10.8,"rainfall":0,"humidity":72},{"day":29,"tempHigh":24,"tempLow":10.2,"rainfall":0,"humidity":60},{"day":30,"tempHigh":21,"tempLow":10.9,"rainfall":0,"humidity":67},{"day":31,"tempHigh":18.5,"tempLow":11.9,"rainfall":0,"humidity":71}]}},"6":{"years":{"2022":[{"day":1,"tempHigh":20,"tempLow":11.4,"rainfall":0,"humidity":73},{"day":2,"tempHigh":17.6,"tempLow":12.2,"rainfall":0,"humidity":76},{"day":3,"tempHigh":16,"tempLow":12.2,"rainfall":0,"humidity":90},{"day":4,"tempHigh":16.8,"tempLow":11.9,"rainfall":0,"humidity":80},{"day":5,"tempHigh":17.5,"tempLow":14.9,"rainfall":7,"humidity":92},{"day":6,"tempHigh":18.9,"tempLow":12.6,"rainfall":0,"humidity":81},{"day":7,"tempHigh":17.2,"tempLow":12.4,"rainfall":0,"humidity":80},{"day":8,"tempHigh":17.5,"tempLow":13.4,"rainfall":0,"humidity":78},{"day":9,"tempHigh":24.1,"tempLow":12.3,"rainfall":0,"humidity":65},{"day":10,"tempHigh":27.5,"tempLow":14.9,"rainfall":0,"humidity":70},{"day":11,"tempHigh":20.7,"tempLow":14.8,"rainfall":0,"humidity":84},{"day":12,"tempHigh":17.5,"tempLow":14,"rainfall":0.4,"humidity":89},{"day":13,"tempHigh":19.8,"tempLow":12.1,"rainfall":0,"humidity":65},{"day":14,"tempHigh":21,"tempLow":12.9,"rainfall":0,"humidity":68},{"day":15,"tempHigh":19.6,"tempLow":13.1,"rainfall":0,"humidity":75},{"day":16,"tempHigh":17.2,"tempLow":12.6,"rainfall":0,"humidity":75},{"day":17,"tempHigh":16.1,"tempLow":12.1,"rainfall":0.1,"humidity":76},{"day":18,"tempHigh":17.6,"tempLow":11.4,"rainfall":0,"humidity":74},{"day":19,"tempHigh":20.6,"tempLow":11.7,"rainfall":0,"humidity":71},{"day":20,"tempHigh":23.9,"tempLow":12.7,"rainfall":0,"humidity":66},{"day":21,"tempHigh":28.6,"tempLow":15.1,"rainfall":0,"humidity":54},{"day":22,"tempHigh":22,"tempLow":14.6,"rainfall":0,"humidity":71},{"day":23,"tempHigh":15.6,"tempLow":12,"rainfall":0,"humidity":90},{"day":24,"tempHigh":15.8,"tempLow":11.9,"rainfall":0,"humidity":86},{"day":25,"tempHigh":16.3,"tempLow":12.4,"rainfall":0,"humidity":87},{"day":26,"tempHigh":15.5,"tempLow":12.3,"rainfall":0,"humidity":91},{"day":27,"tempHigh":18,"tempLow":12.1,"rainfall":0,"humidity":85},{"day":28,"tempHigh":19.6,"tempLow":13.4,"rainfall":0,"humidity":74},{"day":29,"tempHigh":15.9,"tempLow":12.6,"rainfall":0,"humidity":84},{"day":30,"tempHigh":15.4,"tempLow":11.9,"rainfall":0,"humidity":84}],"2023":[{"day":1,"tempHigh":16.2,"tempLow":10.6,"rainfall":0,"humidity":80},{"day":2,"tempHigh":17.2,"tempLow":11.4,"rainfall":0,"humidity":80},{"day":3,"tempHigh":17.2,"tempLow":11.8,"rainfall":0,"humidity":80},{"day":4,"tempHigh":15.8,"tempLow":12.7,"rainfall":0,"humidity":82},{"day":5,"tempHigh":16,"tempLow":11.4,"rainfall":0,"humidity":83},{"day":6,"tempHigh":19.6,"tempLow":13.5,"rainfall":0.3,"humidity":79},{"day":7,"tempHigh":17.6,"tempLow":13.8,"rainfall":0,"humidity":80},{"day":8,"tempHigh":16.4,"tempLow":13.1,"rainfall":0,"humidity":85},{"day":9,"tempHigh":14.9,"tempLow":12.4,"rainfall":0,"humidity":83},{"day":10,"tempHigh":14.9,"tempLow":11.8,"rainfall":0,"humidity":84},{"day":11,"tempHigh":16.6,"tempLow":12.4,"rainfall":0,"humidity":82},{"day":12,"tempHigh":18.1,"tempLow":13.6,"rainfall":0,"humidity":77},{"day":13,"tempHigh":15.9,"tempLow":13.6,"rainfall":0,"humidity":81},{"day":14,"tempHigh":15.8,"tempLow":12.7,"rainfall":0,"humidity":84},{"day":15,"tempHigh":17.4,"tempLow":12.4,"rainfall":0,"humidity":81},{"day":16,"tempHigh":17.4,"tempLow":13.1,"rainfall":0,"humidity":83},{"day":17,"tempHigh":16.5,"tempLow":12.9,"rainfall":0,"humidity":84},{"day":18,"tempHigh":20.2,"tempLow":12.9,"rainfall":0,"humidity":73},{"day":19,"tempHigh":17.5,"tempLow":11.8,"rainfall":0,"humidity":68},{"day":20,"tempHigh":18.3,"tempLow":11.6,"rainfall":0,"humidity":68},{"day":21,"tempHigh":16.1,"tempLow":11.4,"rainfall":0,"humidity":80},{"day":22,"tempHigh":16.5,"tempLow":12.6,"rainfall":0.2,"humidity":78},{"day":23,"tempHigh":16.4,"tempLow":13.3,"rainfall":0.8,"humidity":79},{"day":24,"tempHigh":15.6,"tempLow":12.3,"rainfall":0,"humidity":83},{"day":25,"tempHigh":15.4,"tempLow":12.4,"rainfall":0.1,"humidity":83},{"day":26,"tempHigh":15.6,"tempLow":12.4,"rainfall":0,"humidity":83},{"day":27,"tempHigh":16.3,"tempLow":12.1,"rainfall":0,"humidity":81},{"day":28,"tempHigh":15.8,"tempLow":11.5,"rainfall":0,"humidity":83},{"day":29,"tempHigh":16.5,"tempLow":10.9,"rainfall":0,"humidity":82},{"day":30,"tempHigh":18,"tempLow":12.2,"rainfall":0,"humidity":78}],"2024":[{"day":1,"tempHigh":21.1,"tempLow":11.4,"rainfall":0,"humidity":69},{"day":2,"tempHigh":20.9,"tempLow":12.1,"rainfall":0,"humidity":76},{"day":3,"tempHigh":17.1,"tempLow":12.6,"rainfall":0,"humidity":85},{"day":4,"tempHigh":30.5,"tempLow":11.3,"rainfall":0,"humidity":60},{"day":5,"tempHigh":24.5,"tempLow":13.8,"rainfall":0,"humidity":63},{"day":6,"tempHigh":17,"tempLow":12.4,"rainfall":0,"humidity":72},{"day":7,"tempHigh":18,"tempLow":12,"rainfall":0,"humidity":75},{"day":8,"tempHigh":17.9,"tempLow":12.2,"rainfall":0,"humidity":73},{"day":9,"tempHigh":19.5,"tempLow":12.4,"rainfall":0,"humidity":72},{"day":10,"tempHigh":18,"tempLow":11.9,"rainfall":0,"humidity":77},{"day":11,"tempHigh":24,"tempLow":11.9,"rainfall":0,"humidity":66},{"day":12,"tempHigh":18.9,"tempLow":12.6,"rainfall":0,"humidity":72},{"day":13,"tempHigh":16.2,"tempLow":11.6,"rainfall":0,"humidity":76},{"day":14,"tempHigh":22.9,"tempLow":11.5,"rainfall":0,"humidity":64},{"day":15,"tempHigh":23.7,"tempLow":11.4,"rainfall":0,"humidity":59},{"day":16,"tempHigh":23.8,"tempLow":11.8,"rainfall":0,"humidity":56},{"day":17,"tempHigh":24.1,"tempLow":11.9,"rainfall":0,"humidity":50},{"day":18,"tempHigh":21.9,"tempLow":11.6,"rainfall":0,"humidity":59},{"day":19,"tempHigh":15.8,"tempLow":11.3,"rainfall":0,"humidity":79},{"day":20,"tempHigh":16.6,"tempLow":10.8,"rainfall":0,"humidity":82},{"day":21,"tempHigh":16.2,"tempLow":11.6,"rainfall":0,"humidity":81},{"day":22,"tempHigh":18.5,"tempLow":11.4,"rainfall":0,"humidity":75},{"day":23,"tempHigh":17.2,"tempLow":11.6,"rainfall":0,"humidity":76},{"day":24,"tempHigh":18,"tempLow":11.6,"rainfall":0,"humidity":77},{"day":25,"tempHigh":17.5,"tempLow":11.4,"rainfall":0,"humidity":78},{"day":26,"tempHigh":18.2,"tempLow":11.6,"rainfall":0,"humidity":80},{"day":27,"tempHigh":21.9,"tempLow":12,"rainfall":0,"humidity":69},{"day":28,"tempHigh":19.8,"tempLow":11.6,"rainfall":0,"humidity":74},{"day":29,"tempHigh":19.6,"tempLow":12.1,"rainfall":0,"humidity":70},{"day":30,"tempHigh":25.2,"tempLow":14.2,"rainfall":0,"humidity":61}]}},"7":{"years":{"2022":[{"day":1,"tempHigh":16,"tempLow":11.9,"rainfall":0,"humidity":86},{"day":2,"tempHigh":16.1,"tempLow":12.2,"rainfall":0.1,"humidity":85},{"day":3,"tempHigh":15.8,"tempLow":13.1,"rainfall":0,"humidity":81},{"day":4,"tempHigh":19.1,"tempLow":13.6,"rainfall":0,"humidity":83},{"day":5,"tempHigh":17.6,"tempLow":13.8,"rainfall":0,"humidity":91},{"day":6,"tempHigh":18.5,"tempLow":13.8,"rainfall":0.1,"humidity":88},{"day":7,"tempHigh":18.4,"tempLow":12.3,"rainfall":0,"humidity":84},{"day":8,"tempHigh":21.5,"tempLow":13.8,"rainfall":0,"humidity":79},{"day":9,"tempHigh":17.6,"tempLow":13.8,"rainfall":0,"humidity":83},{"day":10,"tempHigh":16.7,"tempLow":13.6,"rainfall":0,"humidity":85},{"day":11,"tempHigh":17.8,"tempLow":13.6,"rainfall":0,"humidity":89},{"day":12,"tempHigh":18.4,"tempLow":13.9,"rainfall":0.1,"humidity":87},{"day":13,"tempHigh":17.7,"tempLow":14.2,"rainfall":0.1,"humidity":84},{"day":14,"tempHigh":20,"tempLow":13.8,"rainfall":0,"humidity":79},{"day":15,"tempHigh":18.6,"tempLow":13.4,"rainfall":0,"humidity":80},{"day":16,"tempHigh":20.1,"tempLow":13.3,"rainfall":0,"humidity":81},{"day":17,"tempHigh":18.6,"tempLow":13.6,"rainfall":0,"humidity":83},{"day":18,"tempHigh":16.2,"tempLow":13.6,"rainfall":0,"humidity":84},{"day":19,"tempHigh":16.2,"tempLow":12.4,"rainfall":0,"humidity":86},{"day":20,"tempHigh":16.3,"tempLow":12.4,"rainfall":0,"humidity":89},{"day":21,"tempHigh":15.6,"tempLow":11.3,"rainfall":0,"humidity":88},{"day":22,"tempHigh":17.1,"tempLow":12.6,"rainfall":0,"humidity":82},{"day":23,"tempHigh":14.9,"tempLow":11.8,"rainfall":0,"humidity":88},{"day":24,"tempHigh":16.6,"tempLow":12.3,"rainfall":0,"humidity":87},{"day":25,"tempHigh":16.4,"tempLow":12.3,"rainfall":0,"humidity":86},{"day":26,"tempHigh":17,"tempLow":14.6,"rainfall":0,"humidity":82},{"day":27,"tempHigh":16.9,"tempLow":12.6,"rainfall":0,"humidity":85},{"day":28,"tempHigh":14.8,"tempLow":12.1,"rainfall":0,"humidity":92},{"day":29,"tempHigh":15.6,"tempLow":12.9,"rainfall":0,"humidity":90},{"day":30,"tempHigh":16.1,"tempLow":13.1,"rainfall":0,"humidity":89},{"day":31,"tempHigh":17,"tempLow":13.7,"rainfall":0,"humidity":90}],"2023":[{"day":1,"tempHigh":19.9,"tempLow":12,"rainfall":0,"humidity":77},{"day":2,"tempHigh":20.5,"tempLow":13,"rainfall":0,"humidity":77},{"day":3,"tempHigh":17.1,"tempLow":13,"rainfall":0,"humidity":85},{"day":4,"tempHigh":17.4,"tempLow":12.9,"rainfall":0,"humidity":80},{"day":5,"tempHigh":17.2,"tempLow":13,"rainfall":0,"humidity":80},{"day":6,"tempHigh":16.9,"tempLow":12.8,"rainfall":0,"humidity":82},{"day":7,"tempHigh":16.8,"tempLow":12.1,"rainfall":0,"humidity":80},{"day":8,"tempHigh":17.9,"tempLow":11.9,"rainfall":0,"humidity":78},{"day":9,"tempHigh":17,"tempLow":11.9,"rainfall":0,"humidity":80},{"day":10,"tempHigh":19.9,"tempLow":11.7,"rainfall":0,"humidity":79},{"day":11,"tempHigh":18.2,"tempLow":12.1,"rainfall":0,"humidity":80},{"day":12,"tempHigh":18.2,"tempLow":12,"rainfall":0,"humidity":83},{"day":13,"tempHigh":20.2,"tempLow":13,"rainfall":0,"humidity":77},{"day":14,"tempHigh":19.5,"tempLow":12.1,"rainfall":0,"humidity":81},{"day":15,"tempHigh":18,"tempLow":11.6,"rainfall":0,"humidity":80},{"day":16,"tempHigh":21.6,"tempLow":13.1,"rainfall":0,"humidity":74},{"day":17,"tempHigh":20.2,"tempLow":13.5,"rainfall":0,"humidity":72},{"day":18,"tempHigh":17,"tempLow":12.9,"rainfall":0,"humidity":81},{"day":19,"tempHigh":16.5,"tempLow":12.6,"rainfall":0,"humidity":84},{"day":20,"tempHigh":20,"tempLow":12.6,"rainfall":0,"humidity":77},{"day":21,"tempHigh":23.6,"tempLow":13,"rainfall":0,"humidity":70},{"day":22,"tempHigh":23.5,"tempLow":13.2,"rainfall":0,"humidity":68},{"day":23,"tempHigh":21.8,"tempLow":14.4,"rainfall":0,"humidity":71},{"day":24,"tempHigh":21.4,"tempLow":13.1,"rainfall":0,"humidity":78},{"day":25,"tempHigh":22.5,"tempLow":13.7,"rainfall":0,"humidity":76},{"day":26,"tempHigh":17.9,"tempLow":13.4,"rainfall":0,"humidity":80},{"day":27,"tempHigh":19.2,"tempLow":13.4,"rainfall":0,"humidity":76},{"day":28,"tempHigh":21.8,"tempLow":13.1,"rainfall":0,"humidity":75},{"day":29,"tempHigh":21,"tempLow":13,"rainfall":0,"humidity":76},{"day":30,"tempHigh":21.4,"tempLow":12.6,"rainfall":0,"humidity":74},{"day":31,"tempHigh":20.9,"tempLow":12.9,"rainfall":0,"humidity":77}],"2024":[{"day":1,"tempHigh":23.2,"tempLow":12.9,"rainfall":0,"humidity":68},{"day":2,"tempHigh":23.9,"tempLow":12.9,"rainfall":0,"humidity":68},{"day":3,"tempHigh":24.5,"tempLow":12.9,"rainfall":0,"humidity":71},{"day":4,"tempHigh":19.3,"tempLow":12.8,"rainfall":0,"humidity":81},{"day":5,"tempHigh":20.2,"tempLow":11.9,"rainfall":0,"humidity":79},{"day":6,"tempHigh":20.7,"tempLow":14.1,"rainfall":0,"humidity":73},{"day":7,"tempHigh":20,"tempLow":13.6,"rainfall":0,"humidity":79},{"day":8,"tempHigh":18.8,"tempLow":13,"rainfall":0,"humidity":78},{"day":9,"tempHigh":19.3,"tempLow":14.1,"rainfall":0,"humidity":83},{"day":10,"tempHigh":20.5,"tempLow":13.6,"rainfall":0,"humidity":80},{"day":11,"tempHigh":21.8,"tempLow":12.7,"rainfall":0,"humidity":75},{"day":12,"tempHigh":19,"tempLow":13.2,"rainfall":0,"humidity":79},{"day":13,"tempHigh":18.7,"tempLow":11.8,"rainfall":0,"humidity":83},{"day":14,"tempHigh":18.1,"tempLow":14.1,"rainfall":0,"humidity":83},{"day":15,"tempHigh":18.5,"tempLow":13.4,"rainfall":0,"humidity":81},{"day":16,"tempHigh":18.9,"tempLow":13.1,"rainfall":0,"humidity":80},{"day":17,"tempHigh":21,"tempLow":14.1,"rainfall":0,"humidity":76},{"day":18,"tempHigh":22.8,"tempLow":13.9,"rainfall":0,"humidity":72},{"day":19,"tempHigh":30,"tempLow":14.3,"rainfall":0,"humidity":61},{"day":20,"tempHigh":25.9,"tempLow":15.1,"rainfall":0,"humidity":68},{"day":21,"tempHigh":20.9,"tempLow":13.8,"rainfall":0,"humidity":78},{"day":22,"tempHigh":20.1,"tempLow":13.2,"rainfall":0,"humidity":79},{"day":23,"tempHigh":22.5,"tempLow":14.1,"rainfall":0,"humidity":71},{"day":24,"tempHigh":22.1,"tempLow":14.9,"rainfall":0,"humidity":72},{"day":25,"tempHigh":18.5,"tempLow":13.6,"rainfall":0,"humidity":79},{"day":26,"tempHigh":18.1,"tempLow":13.5,"rainfall":0,"humidity":78},{"day":27,"tempHigh":16.7,"tempLow":13.3,"rainfall":0.4,"humidity":80},{"day":28,"tempHigh":18.5,"tempLow":13,"rainfall":0,"humidity":81},{"day":29,"tempHigh":18.9,"tempLow":13.6,"rainfall":0,"humidity":84},{"day":30,"tempHigh":18.8,"tempLow":13.8,"rainfall":0,"humidity":88},{"day":31,"tempHigh":17.8,"tempLow":13,"rainfall":0,"humidity":88}]}},"8":{"years":{"2022":[{"day":1,"tempHigh":20.4,"tempLow":13.8,"rainfall":0.3,"humidity":82},{"day":2,"tempHigh":18.6,"tempLow":14.4,"rainfall":0,"humidity":84},{"day":3,"tempHigh":17.4,"tempLow":13.4,"rainfall":0.2,"humidity":87},{"day":4,"tempHigh":18.9,"tempLow":14.7,"rainfall":0,"humidity":83},{"day":5,"tempHigh":19.2,"tempLow":15.7,"rainfall":0,"humidity":81},{"day":6,"tempHigh":19.9,"tempLow":16.5,"rainfall":0,"humidity":79},{"day":7,"tempHigh":18.6,"tempLow":15.1,"rainfall":0,"humidity":86},{"day":8,"tempHigh":19,"tempLow":14.7,"rainfall":0,"humidity":85},{"day":9,"tempHigh":18.7,"tempLow":15.8,"rainfall":0,"humidity":84},{"day":10,"tempHigh":19.8,"tempLow":15.9,"rainfall":0,"humidity":83},{"day":11,"tempHigh":19.9,"tempLow":15.4,"rainfall":0,"humidity":83},{"day":12,"tempHigh":20.8,"tempLow":15.4,"rainfall":0,"humidity":78},{"day":13,"tempHigh":21.5,"tempLow":15,"rainfall":0,"humidity":79},{"day":14,"tempHigh":22.8,"tempLow":15.1,"rainfall":0,"humidity":77},{"day":15,"tempHigh":22.5,"tempLow":14.9,"rainfall":0,"humidity":78},{"day":16,"tempHigh":17.6,"tempLow":14.8,"rainfall":0,"humidity":85},{"day":17,"tempHigh":18.4,"tempLow":14.2,"rainfall":0.2,"humidity":86},{"day":18,"tempHigh":17.6,"tempLow":13.1,"rainfall":0,"humidity":92},{"day":19,"tempHigh":20.7,"tempLow":14.4,"rainfall":0,"humidity":82},{"day":20,"tempHigh":17.9,"tempLow":14.4,"rainfall":0,"humidity":85},{"day":21,"tempHigh":18.1,"tempLow":13.1,"rainfall":0,"humidity":86},{"day":22,"tempHigh":25.5,"tempLow":14.4,"rainfall":0,"humidity":79},{"day":23,"tempHigh":21.4,"tempLow":15.5,"rainfall":0,"humidity":83},{"day":24,"tempHigh":17.4,"tempLow":13.9,"rainfall":0.1,"humidity":91},{"day":25,"tempHigh":17.4,"tempLow":14.4,"rainfall":0,"humidity":90},{"day":26,"tempHigh":17.8,"tempLow":14.4,"rainfall":0,"humidity":88},{"day":27,"tempHigh":16.7,"tempLow":13.9,"rainfall":0,"humidity":89},{"day":28,"tempHigh":18.1,"tempLow":14.5,"rainfall":0,"humidity":84},{"day":29,"tempHigh":17,"tempLow":13.4,"rainfall":0,"humidity":88},{"day":30,"tempHigh":16,"tempLow":12.9,"rainfall":0,"humidity":92},{"day":31,"tempHigh":19,"tempLow":13.5,"rainfall":0,"humidity":80}],"2023":[{"day":1,"tempHigh":16.8,"tempLow":13.2,"rainfall":0,"humidity":85},{"day":2,"tempHigh":18.7,"tempLow":13.5,"rainfall":0,"humidity":84},{"day":3,"tempHigh":16.5,"tempLow":12.9,"rainfall":0,"humidity":88},{"day":4,"tempHigh":19.8,"tempLow":12.8,"rainfall":0,"humidity":83},{"day":5,"tempHigh":22.2,"tempLow":13.4,"rainfall":0,"humidity":75},{"day":6,"tempHigh":26.1,"tempLow":14.2,"rainfall":0,"humidity":67},{"day":7,"tempHigh":24,"tempLow":14.2,"rainfall":0,"humidity":75},{"day":8,"tempHigh":18.5,"tempLow":13.9,"rainfall":0,"humidity":86},{"day":9,"tempHigh":18.9,"tempLow":13.8,"rainfall":0,"humidity":85},{"day":10,"tempHigh":18,"tempLow":14,"rainfall":0,"humidity":87},{"day":11,"tempHigh":18.6,"tempLow":13.8,"rainfall":0,"humidity":86},{"day":12,"tempHigh":18.3,"tempLow":13.4,"rainfall":0,"humidity":85},{"day":13,"tempHigh":18.6,"tempLow":13.1,"rainfall":0,"humidity":87},{"day":14,"tempHigh":19.4,"tempLow":12.9,"rainfall":0,"humidity":84},{"day":15,"tempHigh":19.2,"tempLow":12.9,"rainfall":0,"humidity":86},{"day":16,"tempHigh":19.7,"tempLow":14.4,"rainfall":0,"humidity":88},{"day":17,"tempHigh":19.5,"tempLow":15.4,"rainfall":0,"humidity":87},{"day":18,"tempHigh":20.7,"tempLow":15.7,"rainfall":0,"humidity":83},{"day":19,"tempHigh":19.3,"tempLow":15,"rainfall":0,"humidity":85},{"day":20,"tempHigh":25,"tempLow":14.6,"rainfall":0,"humidity":77},{"day":21,"tempHigh":24.6,"tempLow":15.9,"rainfall":0.2,"humidity":75},{"day":22,"tempHigh":22.6,"tempLow":16.5,"rainfall":0,"humidity":80},{"day":23,"tempHigh":28.5,"tempLow":15.9,"rainfall":0,"humidity":67},{"day":24,"tempHigh":23.5,"tempLow":16.6,"rainfall":0,"humidity":77},{"day":25,"tempHigh":19.1,"tempLow":15.1,"rainfall":0,"humidity":82},{"day":26,"tempHigh":19,"tempLow":14.9,"rainfall":0,"humidity":79},{"day":27,"tempHigh":23.2,"tempLow":13.8,"rainfall":0,"humidity":73},{"day":28,"tempHigh":24.6,"tempLow":14.1,"rainfall":0,"humidity":71},{"day":29,"tempHigh":27.8,"tempLow":14.5,"rainfall":0,"humidity":63},{"day":30,"tempHigh":28.9,"tempLow":14.1,"rainfall":0,"humidity":65},{"day":31,"tempHigh":19.6,"tempLow":14.7,"rainfall":0,"humidity":81}],"2024":[{"day":1,"tempHigh":18,"tempLow":13.3,"rainfall":0,"humidity":88},{"day":2,"tempHigh":19.6,"tempLow":13.9,"rainfall":0,"humidity":83},{"day":3,"tempHigh":18.1,"tempLow":14.1,"rainfall":0,"humidity":82},{"day":4,"tempHigh":17.4,"tempLow":13.4,"rainfall":0,"humidity":87},{"day":5,"tempHigh":18.6,"tempLow":12.8,"rainfall":0,"humidity":84},{"day":6,"tempHigh":19.9,"tempLow":13.1,"rainfall":0,"humidity":78},{"day":7,"tempHigh":18.6,"tempLow":13.6,"rainfall":0,"humidity":78},{"day":8,"tempHigh":17,"tempLow":13,"rainfall":0,"humidity":87},{"day":9,"tempHigh":19.4,"tempLow":12.3,"rainfall":0,"humidity":86},{"day":10,"tempHigh":21.2,"tempLow":13,"rainfall":0,"humidity":78},{"day":11,"tempHigh":16.1,"tempLow":12.2,"rainfall":0,"humidity":87},{"day":12,"tempHigh":18.9,"tempLow":13.1,"rainfall":0,"humidity":79},{"day":13,"tempHigh":23.9,"tempLow":13.3,"rainfall":0,"humidity":70},{"day":14,"tempHigh":23.6,"tempLow":13.6,"rainfall":0,"humidity":76},{"day":15,"tempHigh":25.4,"tempLow":13.6,"rainfall":0,"humidity":69},{"day":16,"tempHigh":24.5,"tempLow":13.8,"rainfall":0,"humidity":70},{"day":17,"tempHigh":21.1,"tempLow":14.6,"rainfall":0,"humidity":88},{"day":18,"tempHigh":19.2,"tempLow":13.4,"rainfall":0,"humidity":85},{"day":19,"tempHigh":22,"tempLow":11.8,"rainfall":0,"humidity":71},{"day":20,"tempHigh":26,"tempLow":12.9,"rainfall":0,"humidity":62},{"day":21,"tempHigh":19.3,"tempLow":14,"rainfall":0,"humidity":81},{"day":22,"tempHigh":19,"tempLow":14.1,"rainfall":0.3,"humidity":87},{"day":23,"tempHigh":20.5,"tempLow":13.1,"rainfall":1.1,"humidity":82},{"day":24,"tempHigh":21.1,"tempLow":15.3,"rainfall":1,"humidity":80},{"day":25,"tempHigh":22.6,"tempLow":13.1,"rainfall":0,"humidity":74},{"day":26,"tempHigh":22.4,"tempLow":13.4,"rainfall":0,"humidity":74},{"day":27,"tempHigh":22.4,"tempLow":13.9,"rainfall":0,"humidity":80},{"day":28,"tempHigh":22,"tempLow":13.9,"rainfall":0,"humidity":82},{"day":29,"tempHigh":19.1,"tempLow":14.1,"rainfall":0,"humidity":83},{"day":30,"tempHigh":19,"tempLow":14.3,"rainfall":0,"humidity":80},{"day":31,"tempHigh":19,"tempLow":13.4,"rainfall":0,"humidity":85}]}},"9":{"years":{"2022":[{"day":1,"tempHigh":21,"tempLow":14.6,"rainfall":0,"humidity":72},{"day":2,"tempHigh":20.3,"tempLow":13.9,"rainfall":0,"humidity":78},{"day":3,"tempHigh":23.8,"tempLow":15.4,"rainfall":0,"humidity":71},{"day":4,"tempHigh":23.6,"tempLow":14.8,"rainfall":0,"humidity":74},{"day":5,"tempHigh":26.8,"tempLow":14.6,"rainfall":0,"humidity":66},{"day":6,"tempHigh":37.8,"tempLow":16.2,"rainfall":0,"humidity":65},{"day":7,"tempHigh":20.2,"tempLow":15.9,"rainfall":0,"humidity":82},{"day":8,"tempHigh":21.4,"tempLow":15.9,"rainfall":0,"humidity":73},{"day":9,"tempHigh":18.6,"tempLow":15.9,"rainfall":0,"humidity":82},{"day":10,"tempHigh":20,"tempLow":16,"rainfall":0,"humidity":88},{"day":11,"tempHigh":20.2,"tempLow":16.9,"rainfall":0,"humidity":84},{"day":12,"tempHigh":19.4,"tempLow":15,"rainfall":0,"humidity":84},{"day":13,"tempHigh":18.2,"tempLow":14.3,"rainfall":0,"humidity":85},{"day":14,"tempHigh":18.6,"tempLow":15.4,"rainfall":0.1,"humidity":86},{"day":15,"tempHigh":17.3,"tempLow":14.5,"rainfall":0.1,"humidity":83},{"day":16,"tempHigh":19.8,"tempLow":14.4,"rainfall":0,"humidity":82},{"day":17,"tempHigh":19,"tempLow":14,"rainfall":0.3,"humidity":80},{"day":18,"tempHigh":20.9,"tempLow":16.3,"rainfall":6.6,"humidity":79},{"day":19,"tempHigh":19.5,"tempLow":16,"rainfall":2.4,"humidity":82},{"day":20,"tempHigh":19.4,"tempLow":14.9,"rainfall":0,"humidity":83},{"day":21,"tempHigh":18.3,"tempLow":15.1,"rainfall":1.9,"humidity":85},{"day":22,"tempHigh":20.5,"tempLow":13.9,"rainfall":0,"humidity":82},{"day":23,"tempHigh":21.6,"tempLow":14.4,"rainfall":0,"humidity":83},{"day":24,"tempHigh":19.9,"tempLow":14.6,"rainfall":0,"humidity":89},{"day":25,"tempHigh":17,"tempLow":14.5,"rainfall":0,"humidity":92},{"day":26,"tempHigh":16.5,"tempLow":13.9,"rainfall":0,"humidity":89},{"day":27,"tempHigh":18,"tempLow":14.1,"rainfall":0,"humidity":81},{"day":28,"tempHigh":20.4,"tempLow":14.6,"rainfall":0,"humidity":80},{"day":29,"tempHigh":21,"tempLow":14.8,"rainfall":0,"humidity":80},{"day":30,"tempHigh":19.9,"tempLow":13.7,"rainfall":0,"humidity":87}],"2023":[{"day":1,"tempHigh":19.1,"tempLow":14.7,"rainfall":0.1,"humidity":85},{"day":2,"tempHigh":22.2,"tempLow":15.8,"rainfall":0.4,"humidity":76},{"day":3,"tempHigh":19.3,"tempLow":14.7,"rainfall":0,"humidity":87},{"day":4,"tempHigh":18.5,"tempLow":14.2,"rainfall":0,"humidity":86},{"day":5,"tempHigh":20,"tempLow":14.2,"rainfall":0,"humidity":79},{"day":6,"tempHigh":20,"tempLow":14.4,"rainfall":0,"humidity":79},{"day":7,"tempHigh":18.4,"tempLow":14.6,"rainfall":0,"humidity":81},{"day":8,"tempHigh":21.2,"tempLow":13.6,"rainfall":0,"humidity":80},{"day":9,"tempHigh":20,"tempLow":14.1,"rainfall":0,"humidity":77},{"day":10,"tempHigh":20.3,"tempLow":14.2,"rainfall":0,"humidity":75},{"day":11,"tempHigh":24.5,"tempLow":13.1,"rainfall":0,"humidity":75},{"day":12,"tempHigh":19.7,"tempLow":14.5,"rainfall":0,"humidity":80},{"day":13,"tempHigh":20.3,"tempLow":14.9,"rainfall":0,"humidity":82},{"day":14,"tempHigh":19.7,"tempLow":13.7,"rainfall":0,"humidity":85},{"day":15,"tempHigh":19.2,"tempLow":15.4,"rainfall":0,"humidity":84},{"day":16,"tempHigh":19.9,"tempLow":16,"rainfall":0,"humidity":82},{"day":17,"tempHigh":19.6,"tempLow":15,"rainfall":0,"humidity":83},{"day":18,"tempHigh":19.6,"tempLow":13.5,"rainfall":0.2,"humidity":83},{"day":19,"tempHigh":18.8,"tempLow":13.1,"rainfall":0,"humidity":85},{"day":20,"tempHigh":19.6,"tempLow":13.4,"rainfall":0,"humidity":79},{"day":21,"tempHigh":20.6,"tempLow":12.9,"rainfall":0,"humidity":78},{"day":22,"tempHigh":19,"tempLow":14,"rainfall":0,"humidity":77},{"day":23,"tempHigh":17.8,"tempLow":13.8,"rainfall":0,"humidity":79},{"day":24,"tempHigh":19.1,"tempLow":14,"rainfall":0,"humidity":79},{"day":25,"tempHigh":23.3,"tempLow":14.2,"rainfall":0,"humidity":70},{"day":26,"tempHigh":21.3,"tempLow":15.6,"rainfall":0.7,"humidity":79},{"day":27,"tempHigh":23.8,"tempLow":13.8,"rainfall":0,"humidity":73},{"day":28,"tempHigh":23,"tempLow":12.9,"rainfall":0,"humidity":75},{"day":29,"tempHigh":20.2,"tempLow":14.4,"rainfall":0.2,"humidity":80},{"day":30,"tempHigh":17.9,"tempLow":14.2,"rainfall":0.1,"humidity":79}],"2024":[{"day":1,"tempHigh":20.4,"tempLow":13.9,"rainfall":0,"humidity":82},{"day":2,"tempHigh":20.6,"tempLow":14.9,"rainfall":0,"humidity":80},{"day":3,"tempHigh":30.2,"tempLow":12.8,"rainfall":0,"humidity":69},{"day":4,"tempHigh":20.1,"tempLow":14.6,"rainfall":0,"humidity":86},{"day":5,"tempHigh":19.4,"tempLow":13.6,"rainfall":0,"humidity":81},{"day":6,"tempHigh":20.1,"tempLow":13.6,"rainfall":0,"humidity":72},{"day":7,"tempHigh":18.3,"tempLow":13.7,"rainfall":0,"humidity":80},{"day":8,"tempHigh":18,"tempLow":13.3,"rainfall":0,"humidity":85},{"day":9,"tempHigh":18.9,"tempLow":13.1,"rainfall":0,"humidity":86},{"day":10,"tempHigh":17.5,"tempLow":13.7,"rainfall":0,"humidity":82},{"day":11,"tempHigh":23.4,"tempLow":13.4,"rainfall":0,"humidity":76},{"day":12,"tempHigh":21.6,"tempLow":13.4,"rainfall":0,"humidity":75},{"day":13,"tempHigh":20.6,"tempLow":13.6,"rainfall":0,"humidity":79},{"day":14,"tempHigh":18.9,"tempLow":12.8,"rainfall":0,"humidity":83},{"day":15,"tempHigh":18.6,"tempLow":13.1,"rainfall":0,"humidity":81},{"day":16,"tempHigh":19.4,"tempLow":13.1,"rainfall":1.9,"humidity":79},{"day":17,"tempHigh":16.5,"tempLow":12.7,"rainfall":0,"humidity":85},{"day":18,"tempHigh":20.2,"tempLow":13.8,"rainfall":1,"humidity":90},{"day":19,"tempHigh":17.2,"tempLow":12.2,"rainfall":0,"humidity":89},{"day":20,"tempHigh":17.2,"tempLow":12.6,"rainfall":0,"humidity":87},{"day":21,"tempHigh":19.8,"tempLow":12.7,"rainfall":0,"humidity":84},{"day":22,"tempHigh":18.9,"tempLow":13,"rainfall":0,"humidity":85},{"day":23,"tempHigh":33.3,"tempLow":11.9,"rainfall":0,"humidity":71},{"day":24,"tempHigh":24.5,"tempLow":12.8,"rainfall":0,"humidity":79},{"day":25,"tempHigh":17.9,"tempLow":13.9,"rainfall":0,"humidity":84},{"day":26,"tempHigh":18.5,"tempLow":13.4,"rainfall":0,"humidity":82},{"day":27,"tempHigh":26.1,"tempLow":12.8,"rainfall":0,"humidity":75},{"day":28,"tempHigh":17.5,"tempLow":13.4,"rainfall":0,"humidity":87},{"day":29,"tempHigh":18.9,"tempLow":14.1,"rainfall":0,"humidity":77},{"day":30,"tempHigh":28,"tempLow":10.9,"rainfall":0,"humidity":65}]}},"10":{"years":{"2022":[{"day":1,"tempHigh":17.5,"tempLow":13.4,"rainfall":0,"humidity":86},{"day":2,"tempHigh":18.5,"tempLow":15.9,"rainfall":0,"humidity":76},{"day":3,"tempHigh":18.1,"tempLow":14.3,"rainfall":0,"humidity":83},{"day":4,"tempHigh":18.5,"tempLow":14.2,"rainfall":0,"humidity":82},{"day":5,"tempHigh":18.1,"tempLow":14.2,"rainfall":0,"humidity":82},{"day":6,"tempHigh":15.9,"tempLow":13.4,"rainfall":0,"humidity":92},{"day":7,"tempHigh":15.6,"tempLow":13.1,"rainfall":0,"humidity":93},{"day":8,"tempHigh":14.8,"tempLow":12.7,"rainfall":0,"humidity":93},{"day":9,"tempHigh":14.9,"tempLow":12.8,"rainfall":0,"humidity":92},{"day":10,"tempHigh":16.5,"tempLow":11.9,"rainfall":0,"humidity":88},{"day":11,"tempHigh":15.1,"tempLow":10.9,"rainfall":0,"humidity":88},{"day":12,"tempHigh":15.3,"tempLow":12,"rainfall":0,"humidity":87},{"day":13,"tempHigh":14.6,"tempLow":11.8,"rainfall":0,"humidity":90},{"day":14,"tempHigh":14.3,"tempLow":11.6,"rainfall":0,"humidity":93},{"day":15,"tempHigh":16.7,"tempLow":12.6,"rainfall":0,"humidity":85},{"day":16,"tempHigh":17.8,"tempLow":14.3,"rainfall":0,"humidity":81},{"day":17,"tempHigh":18.6,"tempLow":13.1,"rainfall":0,"humidity":89},{"day":18,"tempHigh":26.4,"tempLow":13,"rainfall":0,"humidity":75},{"day":19,"tempHigh":27,"tempLow":15.1,"rainfall":0,"humidity":70},{"day":20,"tempHigh":18,"tempLow":13.8,"rainfall":0,"humidity":77},{"day":21,"tempHigh":15.4,"tempLow":12.2,"rainfall":0,"humidity":85},{"day":22,"tempHigh":19.5,"tempLow":13.9,"rainfall":0,"humidity":71},{"day":23,"tempHigh":20,"tempLow":11.6,"rainfall":0,"humidity":52},{"day":24,"tempHigh":16.9,"tempLow":12.1,"rainfall":0,"humidity":61},{"day":25,"tempHigh":16.9,"tempLow":11.6,"rainfall":0,"humidity":80},{"day":26,"tempHigh":17.8,"tempLow":9.4,"rainfall":0,"humidity":66},{"day":27,"tempHigh":17.6,"tempLow":9.9,"rainfall":0,"humidity":75},{"day":28,"tempHigh":14.9,"tempLow":10.9,"rainfall":0,"humidity":79},{"day":29,"tempHigh":18.3,"tempLow":10.6,"rainfall":0,"humidity":80},{"day":30,"tempHigh":15.9,"tempLow":12.4,"rainfall":0,"humidity":87},{"day":31,"tempHigh":14.2,"tempLow":11.8,"rainfall":0,"humidity":88}],"2023":[{"day":1,"tempHigh":19.5,"tempLow":12.6,"rainfall":0,"humidity":77},{"day":2,"tempHigh":20,"tempLow":12.8,"rainfall":0,"humidity":76},{"day":3,"tempHigh":20.5,"tempLow":12.4,"rainfall":0,"humidity":78},{"day":4,"tempHigh":31.5,"tempLow":14.1,"rainfall":0,"humidity":58},{"day":5,"tempHigh":34,"tempLow":16.6,"rainfall":0,"humidity":48},{"day":6,"tempHigh":34.7,"tempLow":17,"rainfall":0,"humidity":50},{"day":7,"tempHigh":28.9,"tempLow":16.7,"rainfall":0,"humidity":61},{"day":8,"tempHigh":19.2,"tempLow":14.4,"rainfall":0,"humidity":80},{"day":9,"tempHigh":20.1,"tempLow":14.3,"rainfall":3.7,"humidity":78},{"day":10,"tempHigh":18.7,"tempLow":15.1,"rainfall":0.3,"humidity":82},{"day":11,"tempHigh":21,"tempLow":14.1,"rainfall":0,"humidity":69},{"day":12,"tempHigh":22,"tempLow":12,"rainfall":0,"humidity":67},{"day":13,"tempHigh":19,"tempLow":12.2,"rainfall":0,"humidity":78},{"day":14,"tempHigh":20.9,"tempLow":14.4,"rainfall":0.6,"humidity":79},{"day":15,"tempHigh":20.1,"tempLow":14.7,"rainfall":0,"humidity":88},{"day":16,"tempHigh":19.6,"tempLow":14.9,"rainfall":0,"humidity":82},{"day":17,"tempHigh":20.1,"tempLow":14.8,"rainfall":0,"humidity":86},{"day":18,"tempHigh":30.3,"tempLow":13.9,"rainfall":0,"humidity":75},{"day":19,"tempHigh":34.5,"tempLow":13.1,"rainfall":0,"humidity":71},{"day":20,"tempHigh":17.7,"tempLow":14.1,"rainfall":0,"humidity":84},{"day":21,"tempHigh":19.2,"tempLow":13,"rainfall":0.3,"humidity":80},{"day":22,"tempHigh":18.6,"tempLow":15.6,"rainfall":6.3,"humidity":83},{"day":23,"tempHigh":19.2,"tempLow":14.4,"rainfall":0,"humidity":86},{"day":24,"tempHigh":18.2,"tempLow":13.6,"rainfall":0,"humidity":87},{"day":25,"tempHigh":17.2,"tempLow":12.8,"rainfall":0,"humidity":80},{"day":26,"tempHigh":17.5,"tempLow":7.9,"rainfall":0,"humidity":66},{"day":27,"tempHigh":16.1,"tempLow":9.2,"rainfall":0,"humidity":73},{"day":28,"tempHigh":19.5,"tempLow":7.6,"rainfall":0,"humidity":66},{"day":29,"tempHigh":23.1,"tempLow":10,"rainfall":0,"humidity":41},{"day":30,"tempHigh":22.8,"tempLow":8.4,"rainfall":0,"humidity":47},{"day":31,"tempHigh":23.3,"tempLow":7.8,"rainfall":0,"humidity":53}],"2024":[{"day":1,"tempHigh":38,"tempLow":13.8,"rainfall":0,"humidity":45},{"day":2,"tempHigh":33.7,"tempLow":13.6,"rainfall":0,"humidity":57},{"day":3,"tempHigh":23.3,"tempLow":13.3,"rainfall":0,"humidity":74},{"day":4,"tempHigh":23.6,"tempLow":12.9,"rainfall":0,"humidity":73},{"day":5,"tempHigh":36,"tempLow":15.8,"rainfall":0,"humidity":44},{"day":6,"tempHigh":36.5,"tempLow":17.9,"rainfall":0,"humidity":39},{"day":7,"tempHigh":32.4,"tempLow":16.5,"rainfall":0,"humidity":47},{"day":8,"tempHigh":24.8,"tempLow":14.8,"rainfall":0,"humidity":65},{"day":9,"tempHigh":20,"tempLow":13.5,"rainfall":0,"humidity":82},{"day":10,"tempHigh":18.2,"tempLow":14.1,"rainfall":0,"humidity":77},{"day":11,"tempHigh":18.3,"tempLow":13.4,"rainfall":0,"humidity":81},{"day":12,"tempHigh":21.3,"tempLow":15.1,"rainfall":0,"humidity":85},{"day":13,"tempHigh":21.6,"tempLow":16.2,"rainfall":0,"humidity":88},{"day":14,"tempHigh":19.1,"tempLow":13.6,"rainfall":0,"humidity":85},{"day":15,"tempHigh":20.8,"tempLow":12.9,"rainfall":0,"humidity":84},{"day":16,"tempHigh":19.2,"tempLow":13.3,"rainfall":6,"humidity":86},{"day":17,"tempHigh":21.1,"tempLow":11.6,"rainfall":0,"humidity":62},{"day":18,"tempHigh":25,"tempLow":14.6,"rainfall":0,"humidity":23},{"day":19,"tempHigh":28.2,"tempLow":11.8,"rainfall":0,"humidity":32},{"day":20,"tempHigh":26.1,"tempLow":10.8,"rainfall":0,"humidity":50},{"day":21,"tempHigh":17.7,"tempLow":11.4,"rainfall":0,"humidity":87},{"day":22,"tempHigh":16.5,"tempLow":11.7,"rainfall":0,"humidity":81},{"day":23,"tempHigh":20.6,"tempLow":10.1,"rainfall":0,"humidity":74},{"day":24,"tempHigh":24.6,"tempLow":10.6,"rainfall":0,"humidity":48},{"day":25,"tempHigh":23.6,"tempLow":10.2,"rainfall":0,"humidity":61},{"day":26,"tempHigh":21.6,"tempLow":9.8,"rainfall":0,"humidity":82},{"day":27,"tempHigh":18,"tempLow":13.6,"rainfall":0,"humidity":92},{"day":28,"tempHigh":16,"tempLow":12.1,"rainfall":0,"humidity":79},{"day":29,"tempHigh":16,"tempLow":9.9,"rainfall":0,"humidity":68},{"day":30,"tempHigh":16.8,"tempLow":10.4,"rainfall":0,"humidity":78},{"day":31,"tempHigh":15.7,"tempLow":10.6,"rainfall":1.2,"humidity":79}]}},"11":{"years":{"2022":[{"day":1,"tempHigh":14.8,"tempLow":11.6,"rainfall":5.5,"humidity":81},{"day":2,"tempHigh":12.9,"tempLow":10.6,"rainfall":1,"humidity":72},{"day":3,"tempHigh":13.2,"tempLow":7.7,"rainfall":0,"humidity":68},{"day":4,"tempHigh":13.5,"tempLow":9,"rainfall":0,"humidity":84},{"day":5,"tempHigh":15.1,"tempLow":12.2,"rainfall":2.4,"humidity":93},{"day":6,"tempHigh":13.4,"tempLow":11.2,"rainfall":0,"humidity":78},{"day":7,"tempHigh":13.5,"tempLow":9.6,"rainfall":5.8,"humidity":75},{"day":8,"tempHigh":11.9,"tempLow":9.3,"rainfall":24.8,"humidity":78},{"day":9,"tempHigh":12.6,"tempLow":9.1,"rainfall":2.2,"humidity":75},{"day":10,"tempHigh":12.3,"tempLow":7.9,"rainfall":0,"humidity":83},{"day":11,"tempHigh":13.6,"tempLow":8.2,"rainfall":0,"humidity":83},{"day":12,"tempHigh":14,"tempLow":9.8,"rainfall":0.1,"humidity":76},{"day":13,"tempHigh":13.4,"tempLow":8.9,"rainfall":0,"humidity":73},{"day":14,"tempHigh":14.4,"tempLow":6.7,"rainfall":0,"humidity":78},{"day":15,"tempHigh":17.5,"tempLow":7.4,"rainfall":0,"humidity":70},{"day":16,"tempHigh":17,"tempLow":8.6,"rainfall":0,"humidity":69},{"day":17,"tempHigh":14.8,"tempLow":6.8,"rainfall":0,"humidity":78},{"day":18,"tempHigh":13.4,"tempLow":8.8,"rainfall":0.1,"humidity":80},{"day":19,"tempHigh":15.8,"tempLow":8.4,"rainfall":0,"humidity":51},{"day":20,"tempHigh":16.5,"tempLow":7.6,"rainfall":0,"humidity":63},{"day":21,"tempHigh":15.9,"tempLow":7.2,"rainfall":0,"humidity":65},{"day":22,"tempHigh":15.1,"tempLow":5.9,"rainfall":0,"humidity":77},{"day":23,"tempHigh":13.4,"tempLow":7.2,"rainfall":0,"humidity":84},{"day":24,"tempHigh":18.6,"tempLow":8.6,"rainfall":0,"humidity":65},{"day":25,"tempHigh":18,"tempLow":7.7,"rainfall":0,"humidity":71},{"day":26,"tempHigh":15.1,"tempLow":7.8,"rainfall":0,"humidity":79},{"day":27,"tempHigh":13.4,"tempLow":7.2,"rainfall":0,"humidity":86},{"day":28,"tempHigh":14.3,"tempLow":7.9,"rainfall":0,"humidity":80},{"day":29,"tempHigh":11.1,"tempLow":5.2,"rainfall":0,"humidity":70},{"day":30,"tempHigh":12.1,"tempLow":5.6,"rainfall":0,"humidity":82}],"2023":[{"day":1,"tempHigh":25,"tempLow":8.6,"rainfall":0,"humidity":53},{"day":2,"tempHigh":20.1,"tempLow":11.8,"rainfall":0,"humidity":60},{"day":3,"tempHigh":22.9,"tempLow":12.6,"rainfall":0,"humidity":71},{"day":4,"tempHigh":18.9,"tempLow":14.1,"rainfall":0,"humidity":91},{"day":5,"tempHigh":19.2,"tempLow":13.4,"rainfall":3.2,"humidity":88},{"day":6,"tempHigh":18.1,"tempLow":13.7,"rainfall":5.1,"humidity":89},{"day":7,"tempHigh":17.4,"tempLow":11.1,"rainfall":0.4,"humidity":80},{"day":8,"tempHigh":19.1,"tempLow":9.1,"rainfall":0,"humidity":66},{"day":9,"tempHigh":16.8,"tempLow":10.3,"rainfall":0,"humidity":79},{"day":10,"tempHigh":18.3,"tempLow":9.1,"rainfall":0.1,"humidity":76},{"day":11,"tempHigh":18.9,"tempLow":8.9,"rainfall":0,"humidity":74},{"day":12,"tempHigh":18.4,"tempLow":8.9,"rainfall":0,"humidity":78},{"day":13,"tempHigh":16.8,"tempLow":11.7,"rainfall":0,"humidity":85},{"day":14,"tempHigh":19.5,"tempLow":12.9,"rainfall":10.3,"humidity":75},{"day":15,"tempHigh":18.6,"tempLow":11.2,"rainfall":6.2,"humidity":71},{"day":16,"tempHigh":18.9,"tempLow":12.6,"rainfall":12.5,"humidity":87},{"day":17,"tempHigh":18.6,"tempLow":10.6,"rainfall":17.6,"humidity":90},{"day":18,"tempHigh":16.6,"tempLow":13.6,"rainfall":11.8,"humidity":88},{"day":19,"tempHigh":16,"tempLow":9.8,"rainfall":0,"humidity":69},{"day":20,"tempHigh":16.9,"tempLow":7.9,"rainfall":0,"humidity":58},{"day":21,"tempHigh":17.2,"tempLow":8.1,"rainfall":0,"humidity":78},{"day":22,"tempHigh":17.7,"tempLow":8.3,"rainfall":0,"humidity":76},{"day":23,"tempHigh":16.5,"tempLow":8.5,"rainfall":0,"humidity":78},{"day":24,"tempHigh":15,"tempLow":6.2,"rainfall":0,"humidity":54},{"day":25,"tempHigh":15.4,"tempLow":6.4,"rainfall":0,"humidity":55},{"day":26,"tempHigh":15.6,"tempLow":6.9,"rainfall":0,"humidity":60},{"day":27,"tempHigh":15.9,"tempLow":5.7,"rainfall":0,"humidity":72},{"day":28,"tempHigh":16.4,"tempLow":6.4,"rainfall":0,"humidity":74},{"day":29,"tempHigh":14.1,"tempLow":8.9,"rainfall":11.4,"humidity":78},{"day":30,"tempHigh":15.3,"tempLow":8.7,"rainfall":0,"humidity":82}],"2024":[{"day":1,"tempHigh":17.1,"tempLow":9.8,"rainfall":0.7,"humidity":80},{"day":2,"tempHigh":16.6,"tempLow":12.1,"rainfall":0.9,"humidity":81},{"day":3,"tempHigh":20.6,"tempLow":12.1,"rainfall":0,"humidity":62},{"day":4,"tempHigh":19.4,"tempLow":12.4,"rainfall":0,"humidity":55},{"day":5,"tempHigh":18.4,"tempLow":10.4,"rainfall":0,"humidity":71},{"day":6,"tempHigh":20.5,"tempLow":13.3,"rainfall":0,"humidity":29},{"day":7,"tempHigh":21,"tempLow":10.1,"rainfall":0,"humidity":37},{"day":8,"tempHigh":20,"tempLow":10.4,"rainfall":0,"humidity":54},{"day":9,"tempHigh":18.5,"tempLow":7.6,"rainfall":0,"humidity":70},{"day":10,"tempHigh":18,"tempLow":9.6,"rainfall":0,"humidity":82},{"day":11,"tempHigh":15.4,"tempLow":11.6,"rainfall":6.8,"humidity":86},{"day":12,"tempHigh":14.8,"tempLow":9.4,"rainfall":0,"humidity":86},{"day":13,"tempHigh":16.8,"tempLow":8.8,"rainfall":3.7,"humidity":85},{"day":14,"tempHigh":14.8,"tempLow":9.7,"rainfall":0.9,"humidity":85},{"day":15,"tempHigh":13.6,"tempLow":8.6,"rainfall":0,"humidity":69},{"day":16,"tempHigh":13.6,"tempLow":7.2,"rainfall":0,"humidity":62},{"day":17,"tempHigh":13.6,"tempLow":7.4,"rainfall":0.6,"humidity":79},{"day":18,"tempHigh":13.9,"tempLow":9.3,"rainfall":0,"humidity":62},{"day":19,"tempHigh":13.7,"tempLow":6.9,"rainfall":0,"humidity":65},{"day":20,"tempHigh":15.1,"tempLow":11.4,"rainfall":37.3,"humidity":63},{"day":21,"tempHigh":16.6,"tempLow":13.2,"rainfall":23,"humidity":81},{"day":22,"tempHigh":16,"tempLow":13.8,"rainfall":57.6,"humidity":91},{"day":23,"tempHigh":13.7,"tempLow":9.4,"rainfall":3.4,"humidity":90},{"day":24,"tempHigh":15.4,"tempLow":7.6,"rainfall":0.2,"humidity":84},{"day":25,"tempHigh":13.7,"tempLow":11.1,"rainfall":10.2,"humidity":90},{"day":26,"tempHigh":13.5,"tempLow":10.2,"rainfall":1.2,"humidity":91},{"day":27,"tempHigh":14.1,"tempLow":8.1,"rainfall":0,"humidity":73},{"day":28,"tempHigh":13.5,"tempLow":6.4,"rainfall":0,"humidity":67},{"day":29,"tempHigh":14.5,"tempLow":7.4,"rainfall":0,"humidity":63},{"day":30,"tempHigh":13.8,"tempLow":6.1,"rainfall":0,"humidity":77}]}},"12":{"years":{"2022":[{"day":1,"tempHigh":11.6,"tempLow":7.8,"rainfall":25,"humidity":78},{"day":2,"tempHigh":11,"tempLow":4.1,"rainfall":0,"humidity":79},{"day":3,"tempHigh":10.6,"tempLow":6.6,"rainfall":8.9,"humidity":88},{"day":4,"tempHigh":13.4,"tempLow":8.6,"rainfall":1.7,"humidity":85},{"day":5,"tempHigh":13,"tempLow":8.7,"rainfall":12.5,"humidity":86},{"day":6,"tempHigh":12.4,"tempLow":8.4,"rainfall":5.4,"humidity":83},{"day":7,"tempHigh":11.1,"tempLow":6.8,"rainfall":0,"humidity":90},{"day":8,"tempHigh":11.8,"tempLow":7.1,"rainfall":4.4,"humidity":88},{"day":9,"tempHigh":10.7,"tempLow":6.1,"rainfall":0,"humidity":86},{"day":10,"tempHigh":13.3,"tempLow":10.1,"rainfall":26.9,"humidity":87},{"day":11,"tempHigh":10.9,"tempLow":7.7,"rainfall":18.3,"humidity":78},{"day":12,"tempHigh":10.2,"tempLow":6.3,"rainfall":3.4,"humidity":80},{"day":13,"tempHigh":10.4,"tempLow":6.6,"rainfall":0,"humidity":82},{"day":14,"tempHigh":10.7,"tempLow":5.1,"rainfall":0,"humidity":85},{"day":15,"tempHigh":10.2,"tempLow":6.2,"rainfall":0,"humidity":81},{"day":16,"tempHigh":11.4,"tempLow":5.6,"rainfall":0,"humidity":78},{"day":17,"tempHigh":11.2,"tempLow":5.4,"rainfall":0,"humidity":76},{"day":18,"tempHigh":10.1,"tempLow":4.6,"rainfall":0,"humidity":88},{"day":19,"tempHigh":8.9,"tempLow":4.1,"rainfall":0,"humidity":86},{"day":20,"tempHigh":10.9,"tempLow":6.1,"rainfall":0.1,"humidity":80},{"day":21,"tempHigh":12.6,"tempLow":5.8,"rainfall":0,"humidity":79},{"day":22,"tempHigh":10.6,"tempLow":7.2,"rainfall":1.6,"humidity":77},{"day":23,"tempHigh":12.6,"tempLow":7.6,"rainfall":0,"humidity":84},{"day":24,"tempHigh":13,"tempLow":7.2,"rainfall":0,"humidity":87},{"day":25,"tempHigh":13.8,"tempLow":8.7,"rainfall":0,"humidity":88},{"day":26,"tempHigh":11.9,"tempLow":7.8,"rainfall":9.1,"humidity":89},{"day":27,"tempHigh":13.9,"tempLow":9.2,"rainfall":26.5,"humidity":91},{"day":28,"tempHigh":11.2,"tempLow":5.8,"rainfall":0.3,"humidity":89},{"day":29,"tempHigh":11.7,"tempLow":9.6,"rainfall":14.3,"humidity":87},{"day":30,"tempHigh":14.3,"tempLow":12.3,"rainfall":16.2,"humidity":96},{"day":31,"tempHigh":13.2,"tempLow":10.6,"rainfall":123,"humidity":92}],"2023":[{"day":1,"tempHigh":14.7,"tempLow":8.9,"rainfall":0.1,"humidity":77},{"day":2,"tempHigh":14.8,"tempLow":12,"rainfall":3.8,"humidity":91},{"day":3,"tempHigh":15.4,"tempLow":10.9,"rainfall":1.1,"humidity":94},{"day":4,"tempHigh":16.4,"tempLow":10.4,"rainfall":0,"humidity":96},{"day":5,"tempHigh":18,"tempLow":10.2,"rainfall":0,"humidity":91},{"day":6,"tempHigh":16.3,"tempLow":9.7,"rainfall":3.5,"humidity":90},{"day":7,"tempHigh":15.1,"tempLow":8.9,"rainfall":1.5,"humidity":80},{"day":8,"tempHigh":14.3,"tempLow":6.2,"rainfall":0,"humidity":78},{"day":9,"tempHigh":13.4,"tempLow":5.6,"rainfall":0,"humidity":68},{"day":10,"tempHigh":13.2,"tempLow":6.9,"rainfall":0,"humidity":75},{"day":11,"tempHigh":13.4,"tempLow":5.9,"rainfall":0,"humidity":85},{"day":12,"tempHigh":12.9,"tempLow":9.8,"rainfall":0,"humidity":94},{"day":13,"tempHigh":15.9,"tempLow":7.7,"rainfall":0,"humidity":75},{"day":14,"tempHigh":14.3,"tempLow":6.6,"rainfall":0,"humidity":78},{"day":15,"tempHigh":16.4,"tempLow":6.8,"rainfall":0,"humidity":72},{"day":16,"tempHigh":17.8,"tempLow":6.6,"rainfall":0,"humidity":70},{"day":17,"tempHigh":13.2,"tempLow":8.1,"rainfall":47.6,"humidity":80},{"day":18,"tempHigh":16.5,"tempLow":10.3,"rainfall":32.7,"humidity":87},{"day":19,"tempHigh":16.4,"tempLow":13.4,"rainfall":15.6,"humidity":89},{"day":20,"tempHigh":13.9,"tempLow":12.3,"rainfall":29.8,"humidity":89},{"day":21,"tempHigh":17.5,"tempLow":10.5,"rainfall":0,"humidity":86},{"day":22,"tempHigh":16,"tempLow":8.9,"rainfall":0,"humidity":91},{"day":23,"tempHigh":13.8,"tempLow":7.9,"rainfall":0,"humidity":86},{"day":24,"tempHigh":12.4,"tempLow":6.4,"rainfall":0,"humidity":86},{"day":25,"tempHigh":13.1,"tempLow":6.4,"rainfall":0,"humidity":86},{"day":26,"tempHigh":13.3,"tempLow":7.5,"rainfall":0,"humidity":92},{"day":27,"tempHigh":15,"tempLow":9.9,"rainfall":4.8,"humidity":86},{"day":28,"tempHigh":16.4,"tempLow":12.1,"rainfall":2.5,"humidity":91},{"day":29,"tempHigh":16.9,"tempLow":11.9,"rainfall":23.1,"humidity":89},{"day":30,"tempHigh":14.8,"tempLow":10.1,"rainfall":8.1,"humidity":87},{"day":31,"tempHigh":13.2,"tempLow":8.9,"rainfall":0.3,"humidity":90}],"2024":[{"day":1,"tempHigh":15.1,"tempLow":8.6,"rainfall":0.2,"humidity":74},{"day":2,"tempHigh":16.5,"tempLow":7,"rainfall":0,"humidity":76},{"day":3,"tempHigh":16.4,"tempLow":7.6,"rainfall":0,"humidity":78},{"day":4,"tempHigh":17,"tempLow":7.8,"rainfall":0,"humidity":82},{"day":5,"tempHigh":16.5,"tempLow":8.9,"rainfall":0.1,"humidity":85},{"day":6,"tempHigh":17.3,"tempLow":7.8,"rainfall":0,"humidity":87},{"day":7,"tempHigh":14.8,"tempLow":7.6,"rainfall":0,"humidity":88},{"day":8,"tempHigh":14.4,"tempLow":8.2,"rainfall":0,"humidity":93},{"day":9,"tempHigh":15.9,"tempLow":6.1,"rainfall":0,"humidity":64},{"day":10,"tempHigh":13.1,"tempLow":6.4,"rainfall":0,"humidity":71},{"day":11,"tempHigh":14.2,"tempLow":5.2,"rainfall":0,"humidity":84},{"day":12,"tempHigh":12.9,"tempLow":10.8,"rainfall":23.9,"humidity":87},{"day":13,"tempHigh":14.4,"tempLow":11,"rainfall":2.6,"humidity":82},{"day":14,"tempHigh":13.2,"tempLow":9.9,"rainfall":46.2,"humidity":83},{"day":15,"tempHigh":12.4,"tempLow":6.9,"rainfall":0,"humidity":89},{"day":16,"tempHigh":12.6,"tempLow":7.5,"rainfall":9,"humidity":91},{"day":17,"tempHigh":13.6,"tempLow":9.3,"rainfall":0,"humidity":94},{"day":18,"tempHigh":13.4,"tempLow":7.1,"rainfall":0,"humidity":90},{"day":19,"tempHigh":12.3,"tempLow":7.3,"rainfall":0,"humidity":87},{"day":20,"tempHigh":12.4,"tempLow":6.3,"rainfall":0,"humidity":95},{"day":21,"tempHigh":15.1,"tempLow":8.9,"rainfall":6.3,"humidity":92},{"day":22,"tempHigh":16.8,"tempLow":11.1,"rainfall":2.3,"humidity":95},{"day":23,"tempHigh":17.6,"tempLow":13.6,"rainfall":2,"humidity":96},{"day":24,"tempHigh":15.1,"tempLow":9.7,"rainfall":14.8,"humidity":87},{"day":25,"tempHigh":11.7,"tempLow":6.2,"rainfall":0,"humidity":87},{"day":26,"tempHigh":14.7,"tempLow":10.1,"rainfall":11.3,"humidity":87},{"day":27,"tempHigh":14.9,"tempLow":11.4,"rainfall":11.4,"humidity":93},{"day":28,"tempHigh":15.8,"tempLow":11.9,"rainfall":4,"humidity":93},{"day":29,"tempHigh":14.6,"tempLow":10.8,"rainfall":7.6,"humidity":92},{"day":30,"tempHigh":13.8,"tempLow":7.2,"rainfall":0,"humidity":83},{"day":31,"tempHigh":12.2,"tempLow":5.7,"rainfall":0,"humidity":84}]}}}